{"statusCode":0,"data":{"id":"33536","name":"Aarumah Multi Cuisine Restaurant","uuid":"1b3e23f6-fb84-4ce2-865c-c9de64a7814e","slug":"aarumah-multi-cuisine-restaurant-velachery-velachery","latLong":"12.9804049,80.22813070000007","city":"Chennai","area":"Velachery","areaPostalCode":"0","areaSlug":"velachery","restaurantSlug":{"restaurant":"aarumah-multi-cuisine-restaurant-velachery-velachery","city":"chennai"},"type":"F","locality":"Velachery","avgRating":3.8,"totalRatings":771,"avgRatingString":"3.8","totalRatingsString":"771 ratings","cloudinaryImageId":"znjtkmkjmeulmahr8sry","coverImageId":null,"brandImageId":null,"fssaiLicenseNo":null,"costForTwo":40000,"costForTwoMsg":"₹400 for two","cuisines":["South Indian","North Indian","Chinese","Chettinad","Arabian"],"minimumOrder":0,"opened":1,"parentId":null,"isNew":false,"isVeg":false,"favorite":false,"tradeCampaignHeaders":[{"header":"Flat 10% off","description":"Flat 10% off on all orders","minCartAmount":0,"discountType":"Percentage"}],"restaurantServiceLine":["REGULAR"],"sla":null,"availability":{"nextCloseMessage":null,"nextOpenTimeMessage":null,"nextCloseTime":"2018-01-20 01:00:00","nextOpenTime":null,"closedReason":null,"closeMessage":null,"opened":true},"labels":[{"title":"Timings","message":"null"},{"title":"Address","message":"100 Feet Road, Sambandam Colony, Tharamani Ring Road, Velachery, Chennai"},{"title":"Cuisines","message":"South Indian,North Indian,Chinese,Chettinad,Arabian"}],"feeDetails":{"restaurant_id":33536,"fees":[{"name":"fix","fee":0,"message":null},{"name":"distance","fee":0,"message":null},{"name":"time","fee":3000,"message":""},{"name":"special","fee":0,"message":null}],"total_fee":3000,"message":null,"title":"Delivery Charge","amount":"3000","icon":null},"thirdPartyAddress":false,"thirdPartyVendor":null,"menu":{"items":{"6731633":{"id":6731633,"name":"Chicken Shawarma Roll","category":"Quick Bites","description":"","cloudinaryImageId":"","recommended":0,"inStock":1,"isVeg":0,"enabled":1,"displayOrder":0,"price":7500,"final_price":6700,"cropChoices":2,"itemScore":0,"itemDiscount":0,"isPopular":0,"showMC":0,"ribbon":{"text":"BESTSELLER","textColor":"#ffffff","topBackgroundColor":"#d53d4c","bottomBackgroundColor":"#b02331"}},"6731634":{"id":6731634,"name":"Chicken Shawarma Plate","category":"Quick Bites","description":"","cloudinaryImageId":"","recommended":0,"inStock":1,"isVeg":0,"enabled":1,"displayOrder":0,"price":9000,"final_price":8100,"cropChoices":2,"itemScore":0,"itemDiscount":0,"isPopular":0,"showMC":0,"ribbon":{"text":"BESTSELLER","textColor":"#ffffff","topBackgroundColor":"#d53d4c","bottomBackgroundColor":"#b02331"}},"6731635":{"id":6731635,"name":"Mexican Chicken Shawarma Roll","category":"Quick Bites","description":"","cloudinaryImageId":"","recommended":0,"inStock":1,"isVeg":0,"enabled":1,"displayOrder":0,"price":9000,"final_price":8100,"cropChoices":2,"itemScore":0,"itemDiscount":0,"isPopular":0,"showMC":0},"6731636":{"id":6731636,"name":"Mexican Chicken Shawarma Plate","category":"Quick Bites","description":"","cloudinaryImageId":"","recommended":0,"inStock":1,"isVeg":0,"enabled":1,"displayOrder":0,"price":10000,"final_price":9000,"cropChoices":2,"itemScore":0,"itemDiscount":0,"isPopular":0,"showMC":0},"6731637":{"id":6731637,"name":"Veg Clear Soup with Noodles","category":"Soups","description":"","cloudinaryImageId":"","recommended":0,"inStock":1,"isVeg":1,"enabled":1,"displayOrder":0,"price":7000,"final_price":6300,"cropChoices":2,"itemScore":0,"itemDiscount":0,"isPopular":0,"showMC":0},"6731638":{"id":6731638,"name":"Veg Sweet corn Soup","category":"Soups","description":"","cloudinaryImageId":"","recommended":0,"inStock":1,"isVeg":1,"enabled":1,"displayOrder":0,"price":8500,"final_price":7600,"cropChoices":2,"itemScore":0,"itemDiscount":0,"isPopular":0,"showMC":0},"6731639":{"id":6731639,"name":"Cream of Veg Soup","category":"Soups","description":"","cloudinaryImageId":"","recommended":0,"inStock":1,"isVeg":1,"enabled":1,"displayOrder":0,"price":8000,"final_price":7200,"cropChoices":2,"itemScore":0,"itemDiscount":0,"isPopular":0,"showMC":0},"6731640":{"id":6731640,"name":"Cream of Mushroom Soup","category":"Soups","description":"","cloudinaryImageId":"","recommended":0,"inStock":1,"isVeg":1,"enabled":1,"displayOrder":0,"price":9000,"final_price":8100,"cropChoices":2,"itemScore":0,"itemDiscount":0,"isPopular":0,"showMC":0},"6731641":{"id":6731641,"name":"Veg Hot & Sour Soup","category":"Soups","description":"","cloudinaryImageId":"","recommended":0,"inStock":1,"isVeg":1,"enabled":1,"displayOrder":0,"price":7000,"final_price":6300,"cropChoices":2,"itemScore":0,"itemDiscount":0,"isPopular":0,"showMC":0},"6731642":{"id":6731642,"name":"Tomato Soup","category":"Soups","description":"","cloudinaryImageId":"","recommended":0,"inStock":1,"isVeg":1,"enabled":1,"displayOrder":0,"price":6000,"final_price":5400,"cropChoices":2,"itemScore":0,"itemDiscount":0,"isPopular":0,"showMC":0},"6731643":{"id":6731643,"name":"Dragon Egg Drop Soup","category":"Soups","description":"","cloudinaryImageId":"","recommended":0,"inStock":1,"isVeg":2,"enabled":1,"displayOrder":0,"price":7000,"final_price":6300,"cropChoices":2,"itemScore":0,"itemDiscount":0,"isPopular":0,"showMC":0},"6731644":{"id":6731644,"name":"Chicken Clear Soup with Noodles","category":"Soups","description":"","cloudinaryImageId":"","recommended":0,"inStock":1,"isVeg":0,"enabled":1,"displayOrder":0,"price":9000,"final_price":8100,"cropChoices":2,"itemScore":0,"itemDiscount":0,"isPopular":0,"showMC":0},"6731645":{"id":6731645,"name":"Chicken Sweet corn Soup","category":"Soups","description":"","cloudinaryImageId":"","recommended":0,"inStock":1,"isVeg":0,"enabled":1,"displayOrder":0,"price":8000,"final_price":7200,"cropChoices":2,"itemScore":0,"itemDiscount":0,"isPopular":0,"showMC":0},"6731646":{"id":6731646,"name":"Cream of Chicken Soup","category":"Soups","description":"","cloudinaryImageId":"","recommended":0,"inStock":1,"isVeg":0,"enabled":1,"displayOrder":0,"price":9000,"final_price":8100,"cropChoices":2,"itemScore":0,"itemDiscount":0,"isPopular":0,"showMC":0},"6731647":{"id":6731647,"name":"Kozhi Milagu Rasam","category":"Soups","description":"Contains Chicken","cloudinaryImageId":"","recommended":0,"inStock":1,"isVeg":0,"enabled":1,"displayOrder":0,"price":9500,"final_price":8500,"cropChoices":2,"itemScore":0,"itemDiscount":0,"isPopular":0,"showMC":0},"6731648":{"id":6731648,"name":"Nattu Kozhi Rasam","category":"Soups","description":"","cloudinaryImageId":"","recommended":0,"inStock":1,"isVeg":0,"enabled":1,"displayOrder":0,"price":9500,"final_price":8500,"cropChoices":2,"itemScore":0,"itemDiscount":0,"isPopular":0,"showMC":0},"6731649":{"id":6731649,"name":"Chicken Hot & Sour Soup","category":"Soups","description":"","cloudinaryImageId":"","recommended":0,"inStock":1,"isVeg":0,"enabled":1,"displayOrder":0,"price":8000,"final_price":7200,"cropChoices":2,"itemScore":0,"itemDiscount":0,"isPopular":0,"showMC":0},"6731650":{"id":6731650,"name":"Chettinad Aatu Elumbu Rasam","category":"Soups","description":"Contains Mutton","cloudinaryImageId":"","recommended":0,"inStock":1,"isVeg":0,"enabled":1,"displayOrder":0,"price":11000,"final_price":9900,"cropChoices":2,"itemScore":0,"itemDiscount":0,"isPopular":0,"showMC":0},"6731651":{"id":6731651,"name":"Mutton Hot & Sour Soup","category":"Soups","description":"","cloudinaryImageId":"","recommended":0,"inStock":1,"isVeg":0,"enabled":1,"displayOrder":0,"price":11000,"final_price":9900,"cropChoices":2,"itemScore":0,"itemDiscount":0,"isPopular":0,"showMC":0},"6731652":{"id":6731652,"name":"Crab Soup","category":"Soups","description":"","cloudinaryImageId":"","recommended":0,"inStock":1,"isVeg":0,"enabled":1,"displayOrder":0,"price":9500,"final_price":8500,"cropChoices":2,"itemScore":0,"itemDiscount":0,"isPopular":0,"showMC":0},"6731653":{"id":6731653,"name":"Green Salad","category":"Salad","description":"","cloudinaryImageId":"","recommended":0,"inStock":1,"isVeg":1,"enabled":1,"displayOrder":0,"price":5000,"final_price":4500,"cropChoices":2,"itemScore":0,"itemDiscount":0,"isPopular":0,"showMC":0},"6731654":{"id":6731654,"name":"Russian Salad","category":"Salad","description":"","cloudinaryImageId":"","recommended":0,"inStock":1,"isVeg":1,"enabled":1,"displayOrder":0,"price":6000,"final_price":5400,"cropChoices":2,"itemScore":0,"itemDiscount":0,"isPopular":0,"showMC":0},"6731655":{"id":6731655,"name":"Tandoori Masala Papad","category":"Indian","description":"","cloudinaryImageId":"","recommended":0,"inStock":1,"isVeg":1,"enabled":1,"displayOrder":0,"price":5000,"final_price":4500,"cropChoices":2,"itemScore":0,"itemDiscount":0,"isPopular":0,"showMC":0},"6731656":{"id":6731656,"name":"Tangy Chilli Pineapple Salad","category":"Salad","description":"","cloudinaryImageId":"","recommended":0,"inStock":1,"isVeg":1,"enabled":1,"displayOrder":0,"price":9000,"final_price":8100,"cropChoices":2,"itemScore":0,"itemDiscount":0,"isPopular":0,"showMC":0},"6731657":{"id":6731657,"name":"Tandoori Chicken Mayonnaise Salad","category":"Salad","description":"","cloudinaryImageId":"","recommended":0,"inStock":1,"isVeg":0,"enabled":1,"displayOrder":0,"price":12000,"final_price":10800,"cropChoices":2,"itemScore":0,"itemDiscount":0,"isPopular":0,"showMC":0,"ribbon":{"text":"MUST TRY","textColor":"#ffffff","topBackgroundColor":"#d53d4c","bottomBackgroundColor":"#b02331"}},"6731658":{"id":6731658,"name":"Aarumah Little Heart","category":"Indian","description":"Chicken breast cooked in tandoori style.","cloudinaryImageId":"","recommended":0,"inStock":1,"isVeg":0,"enabled":1,"displayOrder":0,"price":20000,"final_price":18000,"variants_new":{"exclude_list":[],"variant_groups":[]},"cropChoices":2,"itemScore":0,"itemDiscount":0,"isPopular":0,"showMC":0},"6731659":{"id":6731659,"name":"Namakkal Chicken","category":"Indian","description":"","cloudinaryImageId":"ht7ug5jpd7jx8k0rhdex","recommended":1,"inStock":1,"isVeg":0,"enabled":1,"displayOrder":0,"price":19500,"final_price":17500,"cropChoices":2,"itemScore":0,"itemDiscount":0,"isPopular":0,"showMC":0},"6731660":{"id":6731660,"name":"Chicken Palli Palayam","category":"Indian","description":"","cloudinaryImageId":"manfnotwc6ngk56h06as","recommended":1,"inStock":1,"isVeg":0,"enabled":1,"displayOrder":0,"price":19500,"final_price":17500,"cropChoices":2,"itemScore":0,"itemDiscount":0,"isPopular":0,"showMC":0},"6731661":{"id":6731661,"name":"Pichu Potta Kozhi Fry","category":"Indian","description":"","cloudinaryImageId":"","recommended":0,"inStock":1,"isVeg":0,"enabled":1,"displayOrder":0,"price":19000,"final_price":17100,"cropChoices":2,"itemScore":0,"itemDiscount":0,"isPopular":0,"showMC":0},"6731662":{"id":6731662,"name":"Kongu Chicken Fry","category":"Indian","description":"","cloudinaryImageId":"","recommended":0,"inStock":1,"isVeg":0,"enabled":1,"displayOrder":0,"price":20000,"final_price":18000,"cropChoices":2,"itemScore":0,"itemDiscount":0,"isPopular":0,"showMC":0},"6731663":{"id":6731663,"name":"Ceylon Chicken Fry","category":"Indian","description":"","cloudinaryImageId":"","recommended":0,"inStock":1,"isVeg":0,"enabled":1,"displayOrder":0,"price":19000,"final_price":17100,"cropChoices":2,"itemScore":0,"itemDiscount":0,"isPopular":0,"showMC":0},"6731664":{"id":6731664,"name":"Gulpi Chicken","category":"Indian","description":"","cloudinaryImageId":"","recommended":0,"inStock":1,"isVeg":0,"enabled":1,"displayOrder":0,"price":19500,"final_price":17500,"cropChoices":2,"itemScore":0,"itemDiscount":0,"isPopular":0,"showMC":0},"6731665":{"id":6731665,"name":"Guntur Chicken Fry","category":"Indian","description":"","cloudinaryImageId":"","recommended":0,"inStock":1,"isVeg":0,"enabled":1,"displayOrder":0,"price":19000,"final_price":17100,"cropChoices":2,"itemScore":0,"itemDiscount":0,"isPopular":0,"showMC":0},"6731666":{"id":6731666,"name":"Chicken Seekh Kebab","category":"Indian","description":"","cloudinaryImageId":"","recommended":0,"inStock":1,"isVeg":0,"enabled":1,"displayOrder":0,"price":19000,"final_price":17100,"cropChoices":2,"itemScore":0,"itemDiscount":0,"isPopular":0,"showMC":0},"6731667":{"id":6731667,"name":"Aarumah Tawa Kozhi Roast","category":"Indian","description":"Boneless chicken cooked with south indian spices.","cloudinaryImageId":"","recommended":0,"inStock":1,"isVeg":0,"enabled":1,"displayOrder":0,"price":19500,"final_price":17500,"cropChoices":2,"itemScore":0,"itemDiscount":0,"isPopular":0,"showMC":0},"6731668":{"id":6731668,"name":"Nattu Kozhi Fry","category":"Indian","description":"","cloudinaryImageId":"","recommended":0,"inStock":1,"isVeg":0,"enabled":1,"displayOrder":0,"price":20000,"final_price":18000,"cropChoices":2,"itemScore":0,"itemDiscount":0,"isPopular":0,"showMC":0},"6731669":{"id":6731669,"name":"Mutton Kola Urundai","category":"Indian","description":"","cloudinaryImageId":"","recommended":0,"inStock":1,"isVeg":0,"enabled":1,"displayOrder":0,"price":20000,"final_price":18000,"cropChoices":2,"itemScore":0,"itemDiscount":0,"isPopular":0,"showMC":0},"6731670":{"id":6731670,"name":"Mutton Kari Vadai","category":"Indian","description":"","cloudinaryImageId":"","recommended":0,"inStock":1,"isVeg":0,"enabled":1,"displayOrder":0,"price":19000,"final_price":17100,"cropChoices":2,"itemScore":0,"itemDiscount":0,"isPopular":0,"showMC":0},"6731671":{"id":6731671,"name":"Mango Mutton","category":"Indian","description":"","cloudinaryImageId":"","recommended":0,"inStock":1,"isVeg":0,"enabled":1,"displayOrder":0,"price":21000,"final_price":18900,"cropChoices":2,"itemScore":0,"itemDiscount":0,"isPopular":0,"showMC":0},"6731672":{"id":6731672,"name":"Palak Keema Fry (Mutton)","category":"Indian","description":"","cloudinaryImageId":"","recommended":0,"inStock":1,"isVeg":0,"enabled":1,"displayOrder":0,"price":22000,"final_price":19800,"cropChoices":2,"itemScore":0,"itemDiscount":0,"isPopular":0,"showMC":0},"6731673":{"id":6731673,"name":"Mutton Uppu Kari Varuval","category":"Indian","description":"","cloudinaryImageId":"","recommended":0,"inStock":1,"isVeg":0,"enabled":1,"displayOrder":0,"price":22000,"final_price":19800,"cropChoices":2,"itemScore":0,"itemDiscount":0,"isPopular":0,"showMC":0},"6731674":{"id":6731674,"name":"Mutton Chukka","category":"Indian","description":"","cloudinaryImageId":"k4frp171cj0jxblydsod","recommended":1,"inStock":1,"isVeg":0,"enabled":1,"displayOrder":0,"price":21000,"final_price":18900,"cropChoices":2,"itemScore":0,"itemDiscount":0,"isPopular":0,"showMC":0},"6731675":{"id":6731675,"name":"Nethili Fry","category":"Indian","description":"","cloudinaryImageId":"st42ruhdwsf5xqcxpuxc","recommended":1,"inStock":1,"isVeg":0,"enabled":1,"displayOrder":0,"price":14000,"final_price":12600,"cropChoices":2,"itemScore":0,"itemDiscount":0,"isPopular":0,"showMC":0,"ribbon":{"text":"MUST TRY","textColor":"#ffffff","topBackgroundColor":"#d53d4c","bottomBackgroundColor":"#b02331"}},"6731676":{"id":6731676,"name":"Prawn Fry","category":"Indian","description":"","cloudinaryImageId":"","recommended":0,"inStock":1,"isVeg":0,"enabled":1,"displayOrder":0,"price":21000,"final_price":18900,"cropChoices":2,"itemScore":0,"itemDiscount":0,"isPopular":0,"showMC":0},"6731677":{"id":6731677,"name":"Vanjaram Fish Fry","category":"Indian","description":"","cloudinaryImageId":"cfjwqkhzcajphz5sksgc","recommended":1,"inStock":1,"isVeg":0,"enabled":1,"displayOrder":0,"price":20000,"final_price":18000,"cropChoices":2,"itemScore":0,"itemDiscount":0,"isPopular":0,"showMC":0},"6731678":{"id":6731678,"name":"Fish Fry","category":"Indian","description":"","cloudinaryImageId":"","recommended":0,"inStock":1,"isVeg":0,"enabled":1,"displayOrder":0,"price":15000,"final_price":13500,"cropChoices":2,"itemScore":0,"itemDiscount":0,"isPopular":0,"showMC":0},"6731679":{"id":6731679,"name":"Golden Prawns Fry","category":"Indian","description":"","cloudinaryImageId":"","recommended":0,"inStock":1,"isVeg":0,"enabled":1,"displayOrder":0,"price":20000,"final_price":18000,"cropChoices":2,"itemScore":0,"itemDiscount":0,"isPopular":0,"showMC":0},"6731680":{"id":6731680,"name":"Tandoori Chicken","category":"Indian","description":"","cloudinaryImageId":"kpcwbtxugzmmkeq3wbvj","recommended":1,"inStock":1,"isVeg":0,"enabled":1,"displayOrder":0,"price":18000,"final_price":16200,"variants_new":{"exclude_list":[],"variant_groups":[{"group_id":"627464","name":"Quantity","variations":[{"name":"Half","price":0,"default":1,"id":"2212619","inStock":1,"isVeg":0,"order":1},{"name":"Full","price":11900,"default":0,"id":"2212620","inStock":1,"isVeg":0,"order":2}]}]},"cropChoices":2,"itemScore":0,"itemDiscount":0,"isPopular":0,"showMC":0,"ribbon":{"text":"BESTSELLER","textColor":"#ffffff","topBackgroundColor":"#d53d4c","bottomBackgroundColor":"#b02331"}},"6731681":{"id":6731681,"name":"Malai Tikka","category":"Indian","description":"","cloudinaryImageId":"","recommended":0,"inStock":1,"isVeg":0,"enabled":1,"displayOrder":0,"price":18000,"final_price":16200,"cropChoices":2,"itemScore":0,"itemDiscount":0,"isPopular":0,"showMC":0},"6731682":{"id":6731682,"name":"Hariyali Kebab","category":"Indian","description":"","cloudinaryImageId":"","recommended":0,"inStock":1,"isVeg":0,"enabled":1,"displayOrder":0,"price":18000,"final_price":16200,"cropChoices":2,"itemScore":0,"itemDiscount":0,"isPopular":0,"showMC":0},"6731683":{"id":6731683,"name":"Tangri Kebab","category":"Indian","description":"","cloudinaryImageId":"najxhgwpqgu38gua1hqp","recommended":1,"inStock":1,"isVeg":0,"enabled":1,"displayOrder":0,"price":18000,"final_price":16200,"cropChoices":2,"itemScore":0,"itemDiscount":0,"isPopular":0,"showMC":0},"6731684":{"id":6731684,"name":"Chicken Kebab","category":"Indian","description":"","cloudinaryImageId":"","recommended":0,"inStock":1,"isVeg":0,"enabled":1,"displayOrder":0,"price":18000,"final_price":16200,"cropChoices":2,"itemScore":0,"itemDiscount":0,"isPopular":0,"showMC":0},"6731685":{"id":6731685,"name":"Chicken Seekh Kebab","category":"Indian","description":"","cloudinaryImageId":"","recommended":0,"inStock":1,"isVeg":0,"enabled":1,"displayOrder":0,"price":18000,"final_price":16200,"cropChoices":2,"itemScore":0,"itemDiscount":0,"isPopular":0,"showMC":0},"6731686":{"id":6731686,"name":"Reshmi Kebab","category":"Indian","description":"","cloudinaryImageId":"","recommended":0,"inStock":1,"isVeg":0,"enabled":1,"displayOrder":0,"price":18000,"final_price":16200,"cropChoices":2,"itemScore":0,"itemDiscount":0,"isPopular":0,"showMC":0},"6731687":{"id":6731687,"name":"BBQ Chicken","category":"Indian","description":"","cloudinaryImageId":"","recommended":0,"inStock":1,"isVeg":0,"enabled":1,"displayOrder":0,"price":12000,"final_price":10800,"variants_new":{"exclude_list":[],"variant_groups":[{"group_id":"627465","name":"Quantity","variations":[{"name":"1 Pc","price":0,"default":1,"id":"2212621","inStock":1,"isVeg":0,"order":1},{"name":"Half","price":6000,"default":0,"id":"2212622","inStock":1,"isVeg":0,"order":2},{"name":"Full","price":17900,"default":0,"id":"2212623","inStock":1,"isVeg":0,"order":3}]}]},"cropChoices":2,"itemScore":0,"itemDiscount":0,"isPopular":0,"showMC":0},"6731688":{"id":6731688,"name":"BBQ Chicken in Afghani Style","category":"Indian","description":"","cloudinaryImageId":"","recommended":0,"inStock":1,"isVeg":0,"enabled":1,"displayOrder":0,"price":12000,"final_price":10800,"variants_new":{"exclude_list":[],"variant_groups":[{"group_id":"627466","name":"Quantity","variations":[{"name":"Half","price":0,"default":1,"id":"2212624","inStock":1,"isVeg":0,"order":1},{"name":"Full","price":20000,"default":0,"id":"2212625","inStock":1,"isVeg":0,"order":2}]}]},"cropChoices":2,"itemScore":0,"itemDiscount":0,"isPopular":0,"showMC":0},"6731689":{"id":6731689,"name":"Hot Spicy BBQ Chicken","category":"Indian","description":"","cloudinaryImageId":"","recommended":0,"inStock":1,"isVeg":0,"enabled":1,"displayOrder":0,"price":18000,"final_price":16200,"variants_new":{"exclude_list":[],"variant_groups":[{"group_id":"627467","name":"Quantity","variations":[{"name":"Half","price":0,"default":1,"id":"2212626","inStock":1,"isVeg":0,"order":1},{"name":"Full","price":14000,"default":0,"id":"2212627","inStock":1,"isVeg":0,"order":2}]}]},"cropChoices":2,"itemScore":0,"itemDiscount":0,"isPopular":0,"showMC":0},"6731690":{"id":6731690,"name":"Pepper BBQ Chicken","category":"Indian","description":"","cloudinaryImageId":"","recommended":0,"inStock":1,"isVeg":0,"enabled":1,"displayOrder":0,"price":18000,"final_price":16200,"variants_new":{"exclude_list":[],"variant_groups":[{"group_id":"627468","name":"Quantity","variations":[{"name":"Half","price":0,"default":1,"id":"2212628","inStock":1,"isVeg":0,"order":1},{"name":"Full","price":14000,"default":0,"id":"2212629","inStock":1,"isVeg":0,"order":2}]}]},"cropChoices":2,"itemScore":0,"itemDiscount":0,"isPopular":0,"showMC":0},"6731691":{"id":6731691,"name":"Grill Chicken","category":"Indian","description":"","cloudinaryImageId":"","recommended":0,"inStock":1,"isVeg":0,"enabled":1,"displayOrder":0,"price":18000,"final_price":16200,"variants_new":{"exclude_list":[],"variant_groups":[{"group_id":"627469","name":"Quantity","variations":[{"name":"Half","price":0,"default":1,"id":"2212630","inStock":1,"isVeg":0,"order":1},{"name":"Full","price":11900,"default":0,"id":"2212631","inStock":1,"isVeg":0,"order":2}]}]},"cropChoices":2,"itemScore":0,"itemDiscount":0,"isPopular":0,"showMC":0},"6731692":{"id":6731692,"name":"Assorted BBQ Plates","category":"Indian","description":"Contains Chicken","cloudinaryImageId":"","recommended":0,"inStock":1,"isVeg":0,"enabled":1,"displayOrder":0,"price":72000,"final_price":64800,"cropChoices":2,"itemScore":0,"itemDiscount":0,"isPopular":0,"showMC":0},"6731693":{"id":6731693,"name":"Minced Lamb BBQ","category":"Indian","description":"","cloudinaryImageId":"","recommended":0,"inStock":1,"isVeg":0,"enabled":1,"displayOrder":0,"price":36000,"final_price":32400,"cropChoices":2,"itemScore":0,"itemDiscount":0,"isPopular":0,"showMC":0},"6731694":{"id":6731694,"name":"Fish BBQ","category":"Indian","description":"","cloudinaryImageId":"","recommended":0,"inStock":1,"isVeg":0,"enabled":1,"displayOrder":0,"price":36000,"final_price":32400,"cropChoices":2,"itemScore":0,"itemDiscount":0,"isPopular":0,"showMC":0},"6731695":{"id":6731695,"name":"Tandoori Chicken Platter","category":"Indian","description":"","cloudinaryImageId":"","recommended":0,"inStock":1,"isVeg":0,"enabled":1,"displayOrder":0,"price":36000,"final_price":32400,"cropChoices":2,"itemScore":0,"itemDiscount":0,"isPopular":0,"showMC":0},"6731696":{"id":6731696,"name":"Paneer Butter Masala","category":"Indian","description":"","cloudinaryImageId":"s28z4wxbqgewprvjsc7h","recommended":1,"inStock":1,"isVeg":1,"enabled":1,"displayOrder":0,"price":14000,"final_price":12600,"cropChoices":2,"itemScore":0,"itemDiscount":0,"isPopular":0,"showMC":0},"6731697":{"id":6731697,"name":"Palak Paneer","category":"Indian","description":"","cloudinaryImageId":"","recommended":0,"inStock":1,"isVeg":1,"enabled":1,"displayOrder":0,"price":15000,"final_price":13500,"cropChoices":2,"itemScore":0,"itemDiscount":0,"isPopular":0,"showMC":0},"6731698":{"id":6731698,"name":"Aloo Gobi Masala","category":"Indian","description":"","cloudinaryImageId":"","recommended":0,"inStock":1,"isVeg":1,"enabled":1,"displayOrder":0,"price":13000,"final_price":11700,"cropChoices":2,"itemScore":0,"itemDiscount":0,"isPopular":0,"showMC":0},"6731699":{"id":6731699,"name":"Aloo Jeera","category":"Indian","description":"","cloudinaryImageId":"","recommended":0,"inStock":1,"isVeg":1,"enabled":1,"displayOrder":0,"price":12000,"final_price":10800,"cropChoices":2,"itemScore":0,"itemDiscount":0,"isPopular":0,"showMC":0},"6731700":{"id":6731700,"name":"Chana Masala","category":"Indian","description":"","cloudinaryImageId":"","recommended":0,"inStock":1,"isVeg":1,"enabled":1,"displayOrder":0,"price":12000,"final_price":10800,"cropChoices":2,"itemScore":0,"itemDiscount":0,"isPopular":0,"showMC":0},"6731701":{"id":6731701,"name":"Kadai Paneer","category":"Indian","description":"","cloudinaryImageId":"","recommended":0,"inStock":1,"isVeg":1,"enabled":1,"displayOrder":0,"price":15000,"final_price":13500,"cropChoices":2,"itemScore":0,"itemDiscount":0,"isPopular":0,"showMC":0},"6731702":{"id":6731702,"name":"Mixed Vegetable Curry","category":"Indian","description":"","cloudinaryImageId":"","recommended":0,"inStock":1,"isVeg":1,"enabled":1,"displayOrder":0,"price":15000,"final_price":13500,"cropChoices":2,"itemScore":0,"itemDiscount":0,"isPopular":0,"showMC":0},"6731703":{"id":6731703,"name":"Mushroom Masala","category":"Indian","description":"","cloudinaryImageId":"","recommended":0,"inStock":1,"isVeg":1,"enabled":1,"displayOrder":0,"price":15000,"final_price":13500,"cropChoices":2,"itemScore":0,"itemDiscount":0,"isPopular":0,"showMC":0},"6731704":{"id":6731704,"name":"Egg Curry Masala","category":"Indian","description":"","cloudinaryImageId":"","recommended":0,"inStock":1,"isVeg":2,"enabled":1,"displayOrder":0,"price":10000,"final_price":9000,"cropChoices":2,"itemScore":0,"itemDiscount":0,"isPopular":0,"showMC":0,"ribbon":{"text":"MUST TRY","textColor":"#ffffff","topBackgroundColor":"#d53d4c","bottomBackgroundColor":"#b02331"}},"6731705":{"id":6731705,"name":"Butter Chicken Masala Gravy","category":"Indian","description":"","cloudinaryImageId":"","recommended":0,"inStock":1,"isVeg":0,"enabled":1,"displayOrder":0,"price":18500,"final_price":16600,"cropChoices":2,"itemScore":0,"itemDiscount":0,"isPopular":0,"showMC":0,"ribbon":{"text":"MUST TRY","textColor":"#ffffff","topBackgroundColor":"#d53d4c","bottomBackgroundColor":"#b02331"}},"6731706":{"id":6731706,"name":"Chicken Tikka Masala","category":"Indian","description":"","cloudinaryImageId":"","recommended":0,"inStock":1,"isVeg":0,"enabled":1,"displayOrder":0,"price":19000,"final_price":17100,"cropChoices":2,"itemScore":0,"itemDiscount":0,"isPopular":0,"showMC":0},"6731707":{"id":6731707,"name":"South Indian Chicken Curry","category":"Indian","description":"","cloudinaryImageId":"","recommended":0,"inStock":1,"isVeg":0,"enabled":1,"displayOrder":0,"price":16000,"final_price":14400,"cropChoices":2,"itemScore":0,"itemDiscount":0,"isPopular":0,"showMC":0},"6731708":{"id":6731708,"name":"Kozhi Vellai Korma","category":"Indian","description":"","cloudinaryImageId":"","recommended":0,"inStock":1,"isVeg":0,"enabled":1,"displayOrder":0,"price":21000,"final_price":18900,"cropChoices":2,"itemScore":0,"itemDiscount":0,"isPopular":0,"showMC":0},"6731709":{"id":6731709,"name":"Nattu Kozhi Curry","category":"Indian","description":"","cloudinaryImageId":"","recommended":0,"inStock":1,"isVeg":0,"enabled":1,"displayOrder":0,"price":19000,"final_price":17100,"cropChoices":2,"itemScore":0,"itemDiscount":0,"isPopular":0,"showMC":0},"6731710":{"id":6731710,"name":"Chicken Hyderabadi Masala","category":"Indian","description":"","cloudinaryImageId":"","recommended":0,"inStock":1,"isVeg":0,"enabled":1,"displayOrder":0,"price":20000,"final_price":18000,"cropChoices":2,"itemScore":0,"itemDiscount":0,"isPopular":0,"showMC":0},"6731711":{"id":6731711,"name":"Jeeraga Chicken Curry","category":"Indian","description":"","cloudinaryImageId":"","recommended":0,"inStock":1,"isVeg":0,"enabled":1,"displayOrder":0,"price":19000,"final_price":17100,"cropChoices":2,"itemScore":0,"itemDiscount":0,"isPopular":0,"showMC":0},"6731712":{"id":6731712,"name":"Kongu Nattu Kozhi Kulambu","category":"Indian","description":"","cloudinaryImageId":"","recommended":0,"inStock":1,"isVeg":0,"enabled":1,"displayOrder":0,"price":19000,"final_price":17100,"cropChoices":2,"itemScore":0,"itemDiscount":0,"isPopular":0,"showMC":0,"ribbon":{"text":"MUST TRY","textColor":"#ffffff","topBackgroundColor":"#d53d4c","bottomBackgroundColor":"#b02331"}},"6731713":{"id":6731713,"name":"Chicken Chettinad Masala","category":"Indian","description":"","cloudinaryImageId":"","recommended":0,"inStock":1,"isVeg":0,"enabled":1,"displayOrder":0,"price":19000,"final_price":17100,"cropChoices":2,"itemScore":0,"itemDiscount":0,"isPopular":0,"showMC":0},"6731714":{"id":6731714,"name":"Virudhunagar Mutton Curry","category":"Indian","description":"","cloudinaryImageId":"","recommended":0,"inStock":1,"isVeg":0,"enabled":1,"displayOrder":0,"price":21000,"final_price":18900,"cropChoices":2,"itemScore":0,"itemDiscount":0,"isPopular":0,"showMC":0},"6731715":{"id":6731715,"name":"Thenattu Mutton Kulambu","category":"Indian","description":"","cloudinaryImageId":"","recommended":0,"inStock":1,"isVeg":0,"enabled":1,"displayOrder":0,"price":22000,"final_price":19800,"cropChoices":2,"itemScore":0,"itemDiscount":0,"isPopular":0,"showMC":0},"6731716":{"id":6731716,"name":"Mutton Masala","category":"Indian","description":"","cloudinaryImageId":"","recommended":0,"inStock":1,"isVeg":0,"enabled":1,"displayOrder":0,"price":21000,"final_price":18900,"cropChoices":2,"itemScore":0,"itemDiscount":0,"isPopular":0,"showMC":0},"6731717":{"id":6731717,"name":"Mutton Pepper Masala","category":"Indian","description":"","cloudinaryImageId":"","recommended":0,"inStock":1,"isVeg":0,"enabled":1,"displayOrder":0,"price":21000,"final_price":18900,"cropChoices":2,"itemScore":0,"itemDiscount":0,"isPopular":0,"showMC":0},"6731718":{"id":6731718,"name":"Palak Mutton","category":"Indian","description":"","cloudinaryImageId":"","recommended":0,"inStock":1,"isVeg":0,"enabled":1,"displayOrder":0,"price":20000,"final_price":18000,"cropChoices":2,"itemScore":0,"itemDiscount":0,"isPopular":0,"showMC":0},"6731719":{"id":6731719,"name":"Mutton Urundai Kulambu","category":"Indian","description":"","cloudinaryImageId":"","recommended":0,"inStock":1,"isVeg":0,"enabled":1,"displayOrder":0,"price":20000,"final_price":18000,"cropChoices":2,"itemScore":0,"itemDiscount":0,"isPopular":0,"showMC":0},"6731721":{"id":6731721,"name":"Mutton Keema Masala","category":"Indian","description":"","cloudinaryImageId":"","recommended":0,"inStock":1,"isVeg":0,"enabled":1,"displayOrder":0,"price":19500,"final_price":17500,"cropChoices":2,"itemScore":0,"itemDiscount":0,"isPopular":0,"showMC":0},"6731722":{"id":6731722,"name":"Aarumah Vellattu Korma","category":"Indian","description":"Mutton cooked in south indian coconut based style.","cloudinaryImageId":"","recommended":0,"inStock":1,"isVeg":0,"enabled":1,"displayOrder":0,"price":22000,"final_price":19800,"variants_new":{"exclude_list":[],"variant_groups":[]},"cropChoices":2,"itemScore":0,"itemDiscount":0,"isPopular":0,"showMC":0},"6731723":{"id":6731723,"name":"South Indian Fish Curry","category":"Indian","description":"","cloudinaryImageId":"","recommended":0,"inStock":1,"isVeg":0,"enabled":1,"displayOrder":0,"price":19000,"final_price":17100,"cropChoices":2,"itemScore":0,"itemDiscount":0,"isPopular":0,"showMC":0},"6731724":{"id":6731724,"name":"Kerala Fish Curry","category":"Indian","description":"","cloudinaryImageId":"","recommended":0,"inStock":1,"isVeg":0,"enabled":1,"displayOrder":0,"price":20000,"final_price":18000,"cropChoices":2,"itemScore":0,"itemDiscount":0,"isPopular":0,"showMC":0},"6731725":{"id":6731725,"name":"Coconut Milk Fish Curry","category":"Indian","description":"","cloudinaryImageId":"","recommended":0,"inStock":1,"isVeg":0,"enabled":1,"displayOrder":0,"price":18000,"final_price":16200,"cropChoices":2,"itemScore":0,"itemDiscount":0,"isPopular":0,"showMC":0},"6731726":{"id":6731726,"name":"Nethili Fish Curry","category":"Indian","description":"","cloudinaryImageId":"","recommended":0,"inStock":1,"isVeg":0,"enabled":1,"displayOrder":0,"price":14000,"final_price":12600,"cropChoices":2,"itemScore":0,"itemDiscount":0,"isPopular":0,"showMC":0},"6731727":{"id":6731727,"name":"Mango Fish Curry","category":"Indian","description":"","cloudinaryImageId":"","recommended":0,"inStock":1,"isVeg":0,"enabled":1,"displayOrder":0,"price":21000,"final_price":18900,"cropChoices":2,"itemScore":0,"itemDiscount":0,"isPopular":0,"showMC":0},"6731728":{"id":6731728,"name":"Thenattu Fish Kulambu","category":"Indian","description":"","cloudinaryImageId":"","recommended":0,"inStock":1,"isVeg":0,"enabled":1,"displayOrder":0,"price":22500,"final_price":20200,"cropChoices":2,"itemScore":0,"itemDiscount":0,"isPopular":0,"showMC":0},"6731729":{"id":6731729,"name":"Prawn Masala","category":"Indian","description":"","cloudinaryImageId":"","recommended":0,"inStock":1,"isVeg":0,"enabled":1,"displayOrder":0,"price":21000,"final_price":18900,"cropChoices":2,"itemScore":0,"itemDiscount":0,"isPopular":0,"showMC":0},"6731730":{"id":6731730,"name":"Prawn Pepper Masala","category":"Indian","description":"","cloudinaryImageId":"","recommended":0,"inStock":1,"isVeg":0,"enabled":1,"displayOrder":0,"price":21000,"final_price":18900,"cropChoices":2,"itemScore":0,"itemDiscount":0,"isPopular":0,"showMC":0},"6731731":{"id":6731731,"name":"Malabar Prawn Curry","category":"Indian","description":"","cloudinaryImageId":"","recommended":0,"inStock":1,"isVeg":0,"enabled":1,"displayOrder":0,"price":21000,"final_price":18900,"cropChoices":2,"itemScore":0,"itemDiscount":0,"isPopular":0,"showMC":0},"6731732":{"id":6731732,"name":"Crab Masala","category":"Indian","description":"","cloudinaryImageId":"pkllpwjbhwyb0otwmxa4","recommended":1,"inStock":1,"isVeg":0,"enabled":1,"displayOrder":0,"price":19000,"final_price":17100,"cropChoices":2,"itemScore":0,"itemDiscount":0,"isPopular":0,"showMC":0},"6731733":{"id":6731733,"name":"Ghee Rice","category":"Indian","description":"","cloudinaryImageId":"","recommended":0,"inStock":1,"isVeg":1,"enabled":1,"displayOrder":0,"price":12000,"final_price":10800,"cropChoices":2,"itemScore":0,"itemDiscount":0,"isPopular":0,"showMC":0},"6731734":{"id":6731734,"name":"Jeera Rice","category":"Indian","description":"","cloudinaryImageId":"","recommended":0,"inStock":1,"isVeg":1,"enabled":1,"displayOrder":0,"price":9000,"final_price":8100,"cropChoices":2,"itemScore":0,"itemDiscount":0,"isPopular":0,"showMC":0},"6731735":{"id":6731735,"name":"Steamed Rice (Basmati Rice)","category":"Indian","description":"","cloudinaryImageId":"","recommended":0,"inStock":1,"isVeg":1,"enabled":1,"displayOrder":0,"price":9000,"final_price":8100,"cropChoices":2,"itemScore":0,"itemDiscount":0,"isPopular":0,"showMC":0,"ribbon":{"text":"BESTSELLER","textColor":"#ffffff","topBackgroundColor":"#d53d4c","bottomBackgroundColor":"#b02331"}},"6731736":{"id":6731736,"name":"Chicken Biryani","category":"Indian","description":"","cloudinaryImageId":"wifvnraefcbpbnnw0lhy","recommended":1,"inStock":1,"isVeg":0,"enabled":1,"displayOrder":0,"price":16500,"final_price":14800,"cropChoices":2,"itemScore":0,"itemDiscount":0,"isPopular":0,"showMC":0,"ribbon":{"text":"BESTSELLER","textColor":"#ffffff","topBackgroundColor":"#d53d4c","bottomBackgroundColor":"#b02331"}},"6731737":{"id":6731737,"name":"Chicken 65 Biryani","category":"Indian","description":"","cloudinaryImageId":"","recommended":0,"inStock":1,"isVeg":0,"enabled":1,"displayOrder":0,"price":18000,"final_price":16200,"cropChoices":2,"itemScore":0,"itemDiscount":0,"isPopular":0,"showMC":0},"6731738":{"id":6731738,"name":"Nattu Kozhi Biryani","category":"Indian","description":"","cloudinaryImageId":"","recommended":0,"inStock":1,"isVeg":0,"enabled":1,"displayOrder":0,"price":21000,"final_price":18900,"cropChoices":2,"itemScore":0,"itemDiscount":0,"isPopular":0,"showMC":0},"6731739":{"id":6731739,"name":"Kadaai Biryani","category":"Indian","description":"","cloudinaryImageId":"","recommended":0,"inStock":0,"isVeg":0,"enabled":1,"displayOrder":0,"price":18000,"final_price":16200,"nextAvailableAtMessage":"Next available at 0 am, Sunday","cropChoices":2,"itemScore":0,"itemDiscount":0,"isPopular":0,"showMC":0},"6731740":{"id":6731740,"name":"Mutton Biryani","category":"Indian","description":"","cloudinaryImageId":"","recommended":0,"inStock":1,"isVeg":0,"enabled":1,"displayOrder":0,"price":20000,"final_price":18000,"cropChoices":2,"itemScore":0,"itemDiscount":0,"isPopular":0,"showMC":0,"ribbon":{"text":"BESTSELLER","textColor":"#ffffff","topBackgroundColor":"#d53d4c","bottomBackgroundColor":"#b02331"}},"6731741":{"id":6731741,"name":"Fish Biryani","category":"Indian","description":"","cloudinaryImageId":"","recommended":0,"inStock":1,"isVeg":0,"enabled":1,"displayOrder":0,"price":21000,"final_price":18900,"cropChoices":2,"itemScore":0,"itemDiscount":0,"isPopular":0,"showMC":0},"6731742":{"id":6731742,"name":"Prawn Biryani","category":"Indian","description":"","cloudinaryImageId":"","recommended":0,"inStock":1,"isVeg":0,"enabled":1,"displayOrder":0,"price":21000,"final_price":18900,"cropChoices":2,"itemScore":0,"itemDiscount":0,"isPopular":0,"showMC":0},"6731743":{"id":6731743,"name":"Roti","category":"Indian","description":"","cloudinaryImageId":"","recommended":0,"inStock":1,"isVeg":1,"enabled":1,"displayOrder":0,"price":3000,"final_price":2700,"cropChoices":2,"itemScore":0,"itemDiscount":0,"isPopular":0,"showMC":0},"6731744":{"id":6731744,"name":"Butter Roti","category":"Indian","description":"","cloudinaryImageId":"","recommended":0,"inStock":1,"isVeg":1,"enabled":1,"displayOrder":0,"price":4000,"final_price":3600,"cropChoices":2,"itemScore":0,"itemDiscount":0,"isPopular":0,"showMC":0},"6731745":{"id":6731745,"name":"Parotta","category":"Indian","description":"","cloudinaryImageId":"","recommended":0,"inStock":1,"isVeg":1,"enabled":1,"displayOrder":0,"price":2500,"final_price":2200,"cropChoices":2,"itemScore":0,"itemDiscount":0,"isPopular":0,"showMC":0},"6731746":{"id":6731746,"name":"Naan","category":"Indian","description":"","cloudinaryImageId":"","recommended":0,"inStock":1,"isVeg":1,"enabled":1,"displayOrder":0,"price":3000,"final_price":2700,"cropChoices":2,"itemScore":0,"itemDiscount":0,"isPopular":0,"showMC":0},"6731747":{"id":6731747,"name":"Butter Naan","category":"Indian","description":"","cloudinaryImageId":"","recommended":0,"inStock":1,"isVeg":1,"enabled":1,"displayOrder":0,"price":4000,"final_price":3600,"cropChoices":2,"itemScore":0,"itemDiscount":0,"isPopular":0,"showMC":0},"6731748":{"id":6731748,"name":"Tandoori Parotta","category":"Indian","description":"","cloudinaryImageId":"","recommended":0,"inStock":1,"isVeg":1,"enabled":1,"displayOrder":0,"price":3000,"final_price":2700,"cropChoices":2,"itemScore":0,"itemDiscount":0,"isPopular":0,"showMC":0},"6731749":{"id":6731749,"name":"Plain Kulcha","category":"Indian","description":"","cloudinaryImageId":"","recommended":0,"inStock":1,"isVeg":1,"enabled":1,"displayOrder":0,"price":3500,"final_price":3100,"cropChoices":2,"itemScore":0,"itemDiscount":0,"isPopular":0,"showMC":0},"6731750":{"id":6731750,"name":"Butter Kulcha","category":"Indian","description":"","cloudinaryImageId":"cya4ymyuwlab8oqtmqsb","recommended":1,"inStock":1,"isVeg":1,"enabled":1,"displayOrder":0,"price":4000,"final_price":3600,"cropChoices":2,"itemScore":0,"itemDiscount":0,"isPopular":0,"showMC":0},"6731751":{"id":6731751,"name":"Masala Kulcha","category":"Indian","description":"","cloudinaryImageId":"","recommended":0,"inStock":1,"isVeg":1,"enabled":1,"displayOrder":0,"price":5000,"final_price":4500,"cropChoices":2,"itemScore":0,"itemDiscount":0,"isPopular":0,"showMC":0},"6731752":{"id":6731752,"name":"Plain Rumali Roti","category":"Indian","description":"","cloudinaryImageId":"","recommended":0,"inStock":1,"isVeg":1,"enabled":1,"displayOrder":0,"price":3500,"final_price":3100,"cropChoices":2,"itemScore":0,"itemDiscount":0,"isPopular":0,"showMC":0},"6731753":{"id":6731753,"name":"Butter Rumali Roti","category":"Indian","description":"","cloudinaryImageId":"","recommended":0,"inStock":1,"isVeg":1,"enabled":1,"displayOrder":0,"price":4000,"final_price":3600,"cropChoices":2,"itemScore":0,"itemDiscount":0,"isPopular":0,"showMC":0},"6731754":{"id":6731754,"name":"Gobi Parotta","category":"Indian","description":"","cloudinaryImageId":"","recommended":0,"inStock":1,"isVeg":1,"enabled":1,"displayOrder":0,"price":4000,"final_price":3600,"cropChoices":2,"itemScore":0,"itemDiscount":0,"isPopular":0,"showMC":0},"6731755":{"id":6731755,"name":"Baby corn Salt & Pepper Fry","category":"Chinese","description":"","cloudinaryImageId":"","recommended":0,"inStock":1,"isVeg":1,"enabled":1,"displayOrder":0,"price":14500,"final_price":13000,"cropChoices":2,"itemScore":0,"itemDiscount":0,"isPopular":0,"showMC":0},"6731756":{"id":6731756,"name":"Crispy Honey Chilli Potato","category":"Chinese","description":"","cloudinaryImageId":"","recommended":0,"inStock":1,"isVeg":1,"enabled":1,"displayOrder":0,"price":14000,"final_price":12600,"cropChoices":2,"itemScore":0,"itemDiscount":0,"isPopular":0,"showMC":0},"6731757":{"id":6731757,"name":"Dragon Cauliflower","category":"Chinese","description":"","cloudinaryImageId":"","recommended":0,"inStock":1,"isVeg":1,"enabled":1,"displayOrder":0,"price":14000,"final_price":12600,"cropChoices":2,"itemScore":0,"itemDiscount":0,"isPopular":0,"showMC":0},"6731758":{"id":6731758,"name":"Paneer Tikka","category":"Chinese","description":"","cloudinaryImageId":"","recommended":0,"inStock":1,"isVeg":1,"enabled":1,"displayOrder":0,"price":14500,"final_price":13000,"cropChoices":2,"itemScore":0,"itemDiscount":0,"isPopular":0,"showMC":0},"6731759":{"id":6731759,"name":"Paneer 65","category":"Chinese","description":"","cloudinaryImageId":"","recommended":0,"inStock":1,"isVeg":1,"enabled":1,"displayOrder":0,"price":14500,"final_price":13000,"cropChoices":2,"itemScore":0,"itemDiscount":0,"isPopular":0,"showMC":0},"6731760":{"id":6731760,"name":"Gobi Manchurian Fry","category":"Chinese","description":"","cloudinaryImageId":"","recommended":0,"inStock":1,"isVeg":1,"enabled":1,"displayOrder":0,"price":13500,"final_price":12100,"cropChoices":2,"itemScore":0,"itemDiscount":0,"isPopular":0,"showMC":0},"6731761":{"id":6731761,"name":"Paneer Manchurian Fry","category":"Chinese","description":"","cloudinaryImageId":"","recommended":0,"inStock":1,"isVeg":1,"enabled":1,"displayOrder":0,"price":14000,"final_price":12600,"cropChoices":2,"itemScore":0,"itemDiscount":0,"isPopular":0,"showMC":0},"6731762":{"id":6731762,"name":"Mushroom Manchurian Fry","category":"Chinese","description":"","cloudinaryImageId":"","recommended":0,"inStock":1,"isVeg":1,"enabled":1,"displayOrder":0,"price":14500,"final_price":13000,"cropChoices":2,"itemScore":0,"itemDiscount":0,"isPopular":0,"showMC":0},"6731763":{"id":6731763,"name":"Chilli Mushroom Dry","category":"Chinese","description":"","cloudinaryImageId":"","recommended":0,"inStock":1,"isVeg":1,"enabled":1,"displayOrder":0,"price":14500,"final_price":13000,"cropChoices":2,"itemScore":0,"itemDiscount":0,"isPopular":0,"showMC":0},"6731764":{"id":6731764,"name":"Chilli Gobi Dry","category":"Chinese","description":"","cloudinaryImageId":"","recommended":0,"inStock":1,"isVeg":1,"enabled":1,"displayOrder":0,"price":14500,"final_price":13000,"cropChoices":2,"itemScore":0,"itemDiscount":0,"isPopular":0,"showMC":0},"6731765":{"id":6731765,"name":"Chilli Paneer Dry","category":"Chinese","description":"","cloudinaryImageId":"","recommended":0,"inStock":1,"isVeg":1,"enabled":1,"displayOrder":0,"price":14500,"final_price":13000,"cropChoices":2,"itemScore":0,"itemDiscount":0,"isPopular":0,"showMC":0},"6731766":{"id":6731766,"name":"Veg Manchurian Dry","category":"Chinese","description":"","cloudinaryImageId":"","recommended":0,"inStock":1,"isVeg":1,"enabled":1,"displayOrder":0,"price":14000,"final_price":12600,"cropChoices":2,"itemScore":0,"itemDiscount":0,"isPopular":0,"showMC":0},"6731767":{"id":6731767,"name":"Chilli Egg Dry","category":"Chinese","description":"","cloudinaryImageId":"","recommended":0,"inStock":1,"isVeg":2,"enabled":1,"displayOrder":0,"price":12000,"final_price":10800,"cropChoices":2,"itemScore":0,"itemDiscount":0,"isPopular":0,"showMC":0},"6731768":{"id":6731768,"name":"Crispy Chicken","category":"Chinese","description":"","cloudinaryImageId":"cyklfzgulziv7qidrj6m","recommended":1,"inStock":1,"isVeg":0,"enabled":1,"displayOrder":0,"price":16000,"final_price":14400,"cropChoices":2,"itemScore":0,"itemDiscount":0,"isPopular":0,"showMC":0},"6731769":{"id":6731769,"name":"Chicken Pepper Stick","category":"Chinese","description":"","cloudinaryImageId":"","recommended":0,"inStock":1,"isVeg":0,"enabled":1,"displayOrder":0,"price":16000,"final_price":14400,"cropChoices":2,"itemScore":0,"itemDiscount":0,"isPopular":0,"showMC":0},"6731770":{"id":6731770,"name":"Americn Fried Chicken","category":"Chinese","description":"","cloudinaryImageId":"","recommended":0,"inStock":1,"isVeg":0,"enabled":1,"displayOrder":0,"price":18000,"final_price":16200,"cropChoices":2,"itemScore":0,"itemDiscount":0,"isPopular":0,"showMC":0},"6731771":{"id":6731771,"name":"Drums of Heaven","category":"Chinese","description":"Chicken lollipops tossed in chinese style.","cloudinaryImageId":"","recommended":0,"inStock":1,"isVeg":0,"enabled":1,"displayOrder":0,"price":18000,"final_price":16200,"cropChoices":2,"itemScore":0,"itemDiscount":0,"isPopular":0,"showMC":0},"6731772":{"id":6731772,"name":"Chicken Spring Roll","category":"Chinese","description":"","cloudinaryImageId":"","recommended":0,"inStock":1,"isVeg":0,"enabled":1,"displayOrder":0,"price":18000,"final_price":16200,"cropChoices":2,"itemScore":0,"itemDiscount":0,"isPopular":0,"showMC":0},"6731773":{"id":6731773,"name":"Chicken 65","category":"Chinese","description":"","cloudinaryImageId":"blickccojryycbh2vou5","recommended":1,"inStock":1,"isVeg":0,"enabled":1,"displayOrder":0,"price":18000,"final_price":16200,"cropChoices":2,"itemScore":0,"itemDiscount":0,"isPopular":0,"showMC":0},"6731774":{"id":6731774,"name":"Chicken Lollipop Indian Style","category":"Chinese","description":"","cloudinaryImageId":"","recommended":0,"inStock":1,"isVeg":0,"enabled":1,"displayOrder":0,"price":16000,"final_price":14400,"cropChoices":2,"itemScore":0,"itemDiscount":0,"isPopular":0,"showMC":0},"6731775":{"id":6731775,"name":"Chicken in Choice of Sauce Dry","category":"Chinese","description":"Served in choice of sauce.","cloudinaryImageId":"","recommended":0,"inStock":1,"isVeg":0,"enabled":1,"displayOrder":0,"price":19000,"final_price":17100,"variants_new":{"exclude_list":[],"variant_groups":[{"group_id":"627470","name":"Choice of Sauce","variations":[{"name":"Ginger Sauce","price":0,"default":1,"id":"2212632","inStock":1,"isVeg":1,"order":1},{"name":"Garlic Sauce","price":0,"default":0,"id":"2212633","inStock":1,"isVeg":1,"order":2},{"name":"Manchurian Sauce","price":0,"default":0,"id":"2212634","inStock":1,"isVeg":1,"order":3}]}]},"cropChoices":2,"itemScore":0,"itemDiscount":0,"isPopular":0,"showMC":0},"6731779":{"id":6731779,"name":"Mutton Pepper Dry","category":"Chinese","description":"","cloudinaryImageId":"","recommended":0,"inStock":1,"isVeg":0,"enabled":1,"displayOrder":0,"price":21000,"final_price":18900,"cropChoices":2,"itemScore":0,"itemDiscount":0,"isPopular":0,"showMC":0},"6731781":{"id":6731781,"name":"Chilli Lamb","category":"Chinese","description":"","cloudinaryImageId":"","recommended":0,"inStock":1,"isVeg":0,"enabled":1,"displayOrder":0,"price":22000,"final_price":19800,"cropChoices":2,"itemScore":0,"itemDiscount":0,"isPopular":0,"showMC":0},"6731782":{"id":6731782,"name":"Hongkong Chilli Fish","category":"Chinese","description":"","cloudinaryImageId":"","recommended":0,"inStock":1,"isVeg":0,"enabled":1,"displayOrder":0,"price":18000,"final_price":16200,"cropChoices":2,"itemScore":0,"itemDiscount":0,"isPopular":0,"showMC":0},"6731783":{"id":6731783,"name":"Chilli Fish","category":"Chinese","description":"","cloudinaryImageId":"","recommended":0,"inStock":1,"isVeg":0,"enabled":1,"displayOrder":0,"price":22000,"final_price":19800,"cropChoices":2,"itemScore":0,"itemDiscount":0,"isPopular":0,"showMC":0},"6731784":{"id":6731784,"name":"Fish Manchurian","category":"Chinese","description":"","cloudinaryImageId":"","recommended":0,"inStock":1,"isVeg":0,"enabled":1,"displayOrder":0,"price":20000,"final_price":18000,"cropChoices":2,"itemScore":0,"itemDiscount":0,"isPopular":0,"showMC":0},"6731785":{"id":6731785,"name":"Ginger Fish","category":"Chinese","description":"","cloudinaryImageId":"","recommended":0,"inStock":1,"isVeg":0,"enabled":1,"displayOrder":0,"price":21000,"final_price":18900,"cropChoices":2,"itemScore":0,"itemDiscount":0,"isPopular":0,"showMC":0},"6731786":{"id":6731786,"name":"Fish Finger","category":"Chinese","description":"","cloudinaryImageId":"","recommended":0,"inStock":1,"isVeg":0,"enabled":1,"displayOrder":0,"price":21000,"final_price":18900,"cropChoices":2,"itemScore":0,"itemDiscount":0,"isPopular":0,"showMC":0},"6731787":{"id":6731787,"name":"Fish 65","category":"Chinese","description":"","cloudinaryImageId":"","recommended":0,"inStock":1,"isVeg":0,"enabled":1,"displayOrder":0,"price":20000,"final_price":18000,"cropChoices":2,"itemScore":0,"itemDiscount":0,"isPopular":0,"showMC":0},"6731788":{"id":6731788,"name":"Chilli Prawn Dry","category":"Chinese","description":"","cloudinaryImageId":"o1srnogkf0wh5g1ozxyv","recommended":1,"inStock":1,"isVeg":0,"enabled":1,"displayOrder":0,"price":21000,"final_price":18900,"cropChoices":2,"itemScore":0,"itemDiscount":0,"isPopular":0,"showMC":0},"6731789":{"id":6731789,"name":"Prawn 65","category":"Chinese","description":"","cloudinaryImageId":"","recommended":0,"inStock":1,"isVeg":0,"enabled":1,"displayOrder":0,"price":20000,"final_price":18000,"cropChoices":2,"itemScore":0,"itemDiscount":0,"isPopular":0,"showMC":0},"6731790":{"id":6731790,"name":"Ginger Prawn","category":"Chinese","description":"","cloudinaryImageId":"","recommended":0,"inStock":1,"isVeg":0,"enabled":1,"displayOrder":0,"price":22000,"final_price":19800,"cropChoices":2,"itemScore":0,"itemDiscount":0,"isPopular":0,"showMC":0},"6731791":{"id":6731791,"name":"Crab Lollipop","category":"Chinese","description":"","cloudinaryImageId":"","recommended":0,"inStock":1,"isVeg":0,"enabled":1,"displayOrder":0,"price":18000,"final_price":16200,"cropChoices":2,"itemScore":0,"itemDiscount":0,"isPopular":0,"showMC":0},"6731792":{"id":6731792,"name":"Veg in Hot Garlic Sauce","category":"Chinese","description":"","cloudinaryImageId":"","recommended":0,"inStock":1,"isVeg":1,"enabled":1,"displayOrder":0,"price":15000,"final_price":13500,"cropChoices":2,"itemScore":0,"itemDiscount":0,"isPopular":0,"showMC":0},"6731793":{"id":6731793,"name":"Mushroom Manchurian","category":"Chinese","description":"","cloudinaryImageId":"","recommended":0,"inStock":1,"isVeg":1,"enabled":1,"displayOrder":0,"price":14000,"final_price":12600,"cropChoices":2,"itemScore":0,"itemDiscount":0,"isPopular":0,"showMC":0},"6731794":{"id":6731794,"name":"Paneer Manchurian","category":"Chinese","description":"","cloudinaryImageId":"","recommended":0,"inStock":1,"isVeg":1,"enabled":1,"displayOrder":0,"price":14000,"final_price":12600,"cropChoices":2,"itemScore":0,"itemDiscount":0,"isPopular":0,"showMC":0},"6731795":{"id":6731795,"name":"Gobi Manchurian Gravy","category":"Chinese","description":"","cloudinaryImageId":"","recommended":0,"inStock":1,"isVeg":1,"enabled":1,"displayOrder":0,"price":14000,"final_price":12600,"cropChoices":2,"itemScore":0,"itemDiscount":0,"isPopular":0,"showMC":0},"6731796":{"id":6731796,"name":"Chicken in Hot Garlic Sauce","category":"Chinese","description":"","cloudinaryImageId":"","recommended":0,"inStock":1,"isVeg":0,"enabled":1,"displayOrder":0,"price":18000,"final_price":16200,"cropChoices":2,"itemScore":0,"itemDiscount":0,"isPopular":0,"showMC":0},"6731797":{"id":6731797,"name":"Chilli Chicken Gravy","category":"Chinese","description":"","cloudinaryImageId":"","recommended":0,"inStock":1,"isVeg":0,"enabled":1,"displayOrder":0,"price":18500,"final_price":16600,"cropChoices":2,"itemScore":0,"itemDiscount":0,"isPopular":0,"showMC":0},"6731798":{"id":6731798,"name":"Chicken in Choice of Sauce Dry","category":"Chinese","description":"Served in choice of sauce.","cloudinaryImageId":"","recommended":0,"inStock":1,"isVeg":0,"enabled":1,"displayOrder":0,"price":18000,"final_price":16200,"variants_new":{"exclude_list":[],"variant_groups":[{"group_id":"627471","name":"Choice of Sauce","variations":[{"name":"Schezwan Sauce","price":0,"default":1,"id":"2212635","inStock":1,"isVeg":1,"order":1},{"name":"Manchurian Sauce","price":0,"default":0,"id":"2212636","inStock":1,"isVeg":1,"order":2}]}]},"cropChoices":2,"itemScore":0,"itemDiscount":0,"isPopular":0,"showMC":0},"6731799":{"id":6731799,"name":"Chilli Lamb Gravy","category":"Chinese","description":"","cloudinaryImageId":"","recommended":0,"inStock":1,"isVeg":0,"enabled":1,"displayOrder":0,"price":22000,"final_price":19800,"cropChoices":2,"itemScore":0,"itemDiscount":0,"isPopular":0,"showMC":0},"6731800":{"id":6731800,"name":"Ginger Fish Semi Gravy","category":"Chinese","description":"","cloudinaryImageId":"","recommended":0,"inStock":1,"isVeg":0,"enabled":1,"displayOrder":0,"price":19000,"final_price":17100,"cropChoices":2,"itemScore":0,"itemDiscount":0,"isPopular":0,"showMC":0},"6731801":{"id":6731801,"name":"Chilli Fish Gravy","category":"Chinese","description":"","cloudinaryImageId":"","recommended":0,"inStock":1,"isVeg":0,"enabled":1,"displayOrder":0,"price":19000,"final_price":17100,"cropChoices":2,"itemScore":0,"itemDiscount":0,"isPopular":0,"showMC":0},"6731802":{"id":6731802,"name":"Chilli Prawn Gravy","category":"Chinese","description":"","cloudinaryImageId":"","recommended":0,"inStock":1,"isVeg":0,"enabled":1,"displayOrder":0,"price":21000,"final_price":18900,"cropChoices":2,"itemScore":0,"itemDiscount":0,"isPopular":0,"showMC":0},"6731803":{"id":6731803,"name":"Veg Fried Rice","category":"Chinese","description":"","cloudinaryImageId":"","recommended":0,"inStock":1,"isVeg":1,"enabled":1,"displayOrder":0,"price":14000,"final_price":12600,"cropChoices":2,"itemScore":0,"itemDiscount":0,"isPopular":0,"showMC":0},"6731804":{"id":6731804,"name":"Paneer Fried Rice","category":"Chinese","description":"","cloudinaryImageId":"","recommended":0,"inStock":1,"isVeg":1,"enabled":1,"displayOrder":0,"price":15500,"final_price":13900,"cropChoices":2,"itemScore":0,"itemDiscount":0,"isPopular":0,"showMC":0},"6731805":{"id":6731805,"name":"Mushroom Fried Rice","category":"Chinese","description":"","cloudinaryImageId":"","recommended":0,"inStock":1,"isVeg":1,"enabled":1,"displayOrder":0,"price":15500,"final_price":13900,"cropChoices":2,"itemScore":0,"itemDiscount":0,"isPopular":0,"showMC":0},"6731806":{"id":6731806,"name":"Paneer Schezwan Fried Rice","category":"Chinese","description":"","cloudinaryImageId":"","recommended":0,"inStock":1,"isVeg":1,"enabled":1,"displayOrder":0,"price":16000,"final_price":14400,"cropChoices":2,"itemScore":0,"itemDiscount":0,"isPopular":0,"showMC":0},"6731807":{"id":6731807,"name":"Mushroom Schezwan Fried Rice","category":"Chinese","description":"","cloudinaryImageId":"","recommended":0,"inStock":1,"isVeg":1,"enabled":1,"displayOrder":0,"price":16000,"final_price":14400,"cropChoices":2,"itemScore":0,"itemDiscount":0,"isPopular":0,"showMC":0},"6731808":{"id":6731808,"name":"Gobi Fried Rice","category":"Chinese","description":"","cloudinaryImageId":"","recommended":0,"inStock":1,"isVeg":1,"enabled":1,"displayOrder":0,"price":15000,"final_price":13500,"cropChoices":2,"itemScore":0,"itemDiscount":0,"isPopular":0,"showMC":0},"6731809":{"id":6731809,"name":"Gobi Schezwan Fried Rice","category":"Chinese","description":"","cloudinaryImageId":"","recommended":0,"inStock":1,"isVeg":1,"enabled":1,"displayOrder":0,"price":16000,"final_price":14400,"cropChoices":2,"itemScore":0,"itemDiscount":0,"isPopular":0,"showMC":0},"6731810":{"id":6731810,"name":"Cashewnut Fried Rice","category":"Chinese","description":"","cloudinaryImageId":"","recommended":0,"inStock":1,"isVeg":1,"enabled":1,"displayOrder":0,"price":19000,"final_price":17100,"cropChoices":2,"itemScore":0,"itemDiscount":0,"isPopular":0,"showMC":0},"6731811":{"id":6731811,"name":"Egg Fried Rice","category":"Chinese","description":"","cloudinaryImageId":"","recommended":0,"inStock":1,"isVeg":2,"enabled":1,"displayOrder":0,"price":14000,"final_price":12600,"cropChoices":2,"itemScore":0,"itemDiscount":0,"isPopular":0,"showMC":0},"6731812":{"id":6731812,"name":"Egg Schezwan Fried Rice","category":"Chinese","description":"","cloudinaryImageId":"","recommended":0,"inStock":1,"isVeg":2,"enabled":1,"displayOrder":0,"price":16000,"final_price":14400,"cropChoices":2,"itemScore":0,"itemDiscount":0,"isPopular":0,"showMC":0},"6731813":{"id":6731813,"name":"Chicken Fried Rice","category":"Chinese","description":"","cloudinaryImageId":"","recommended":0,"inStock":1,"isVeg":0,"enabled":1,"displayOrder":0,"price":16000,"final_price":14400,"cropChoices":2,"itemScore":0,"itemDiscount":0,"isPopular":0,"showMC":0,"ribbon":{"text":"BESTSELLER","textColor":"#ffffff","topBackgroundColor":"#d53d4c","bottomBackgroundColor":"#b02331"}},"6731814":{"id":6731814,"name":"Chicken Schezwan Fried Rice","category":"Chinese","description":"","cloudinaryImageId":"","recommended":0,"inStock":1,"isVeg":0,"enabled":1,"displayOrder":0,"price":18000,"final_price":16200,"cropChoices":2,"itemScore":0,"itemDiscount":0,"isPopular":0,"showMC":0,"ribbon":{"text":"BESTSELLER","textColor":"#ffffff","topBackgroundColor":"#d53d4c","bottomBackgroundColor":"#b02331"}},"6731815":{"id":6731815,"name":"Mutton Fried Rice","category":"Chinese","description":"","cloudinaryImageId":"","recommended":0,"inStock":1,"isVeg":0,"enabled":1,"displayOrder":0,"price":18000,"final_price":16200,"cropChoices":2,"itemScore":0,"itemDiscount":0,"isPopular":0,"showMC":0},"6731816":{"id":6731816,"name":"Mutton Schezwan Fried Rice","category":"Chinese","description":"","cloudinaryImageId":"","recommended":0,"inStock":1,"isVeg":0,"enabled":1,"displayOrder":0,"price":20000,"final_price":18000,"cropChoices":2,"itemScore":0,"itemDiscount":0,"isPopular":0,"showMC":0},"6731817":{"id":6731817,"name":"Prawn Fried Rice","category":"Chinese","description":"","cloudinaryImageId":"","recommended":0,"inStock":1,"isVeg":0,"enabled":1,"displayOrder":0,"price":17000,"final_price":15300,"cropChoices":2,"itemScore":0,"itemDiscount":0,"isPopular":0,"showMC":0},"6731818":{"id":6731818,"name":"Prawn Schezwan Fried Rice","category":"Chinese","description":"","cloudinaryImageId":"","recommended":0,"inStock":1,"isVeg":0,"enabled":1,"displayOrder":0,"price":19000,"final_price":17100,"cropChoices":2,"itemScore":0,"itemDiscount":0,"isPopular":0,"showMC":0},"6731819":{"id":6731819,"name":"Mixed Fried Rice","category":"Chinese","description":"","cloudinaryImageId":"","recommended":0,"inStock":1,"isVeg":0,"enabled":1,"displayOrder":0,"price":20000,"final_price":18000,"cropChoices":2,"itemScore":0,"itemDiscount":0,"isPopular":0,"showMC":0},"6731820":{"id":6731820,"name":"Mixed Schezwan Fried Rice","category":"Chinese","description":"","cloudinaryImageId":"","recommended":0,"inStock":1,"isVeg":0,"enabled":1,"displayOrder":0,"price":22000,"final_price":19800,"cropChoices":2,"itemScore":0,"itemDiscount":0,"isPopular":0,"showMC":0},"6731821":{"id":6731821,"name":"Veg Hakka Noodles","category":"Chinese","description":"","cloudinaryImageId":"","recommended":0,"inStock":1,"isVeg":1,"enabled":1,"displayOrder":0,"price":14000,"final_price":12600,"cropChoices":2,"itemScore":0,"itemDiscount":0,"isPopular":0,"showMC":0},"6731822":{"id":6731822,"name":"Paneer Noodles","category":"Chinese","description":"","cloudinaryImageId":"","recommended":0,"inStock":1,"isVeg":1,"enabled":1,"displayOrder":0,"price":15000,"final_price":13500,"cropChoices":2,"itemScore":0,"itemDiscount":0,"isPopular":0,"showMC":0},"6731823":{"id":6731823,"name":"Mushroom Noodles","category":"Chinese","description":"","cloudinaryImageId":"","recommended":0,"inStock":1,"isVeg":1,"enabled":1,"displayOrder":0,"price":15000,"final_price":13500,"cropChoices":2,"itemScore":0,"itemDiscount":0,"isPopular":0,"showMC":0},"6731824":{"id":6731824,"name":"Paneer Schezwan Noodles","category":"Chinese","description":"","cloudinaryImageId":"","recommended":0,"inStock":1,"isVeg":1,"enabled":1,"displayOrder":0,"price":15500,"final_price":13900,"cropChoices":2,"itemScore":0,"itemDiscount":0,"isPopular":0,"showMC":0},"6731825":{"id":6731825,"name":"Mushroom Schezwan Noodles","category":"Chinese","description":"","cloudinaryImageId":"","recommended":0,"inStock":1,"isVeg":1,"enabled":1,"displayOrder":0,"price":15500,"final_price":13900,"cropChoices":2,"itemScore":0,"itemDiscount":0,"isPopular":0,"showMC":0},"6731826":{"id":6731826,"name":"Gobi Noodles","category":"Chinese","description":"","cloudinaryImageId":"","recommended":0,"inStock":1,"isVeg":1,"enabled":1,"displayOrder":0,"price":15000,"final_price":13500,"cropChoices":2,"itemScore":0,"itemDiscount":0,"isPopular":0,"showMC":0},"6731827":{"id":6731827,"name":"Gobi Schezwan Noodles","category":"Chinese","description":"","cloudinaryImageId":"","recommended":0,"inStock":1,"isVeg":1,"enabled":1,"displayOrder":0,"price":16000,"final_price":14400,"cropChoices":2,"itemScore":0,"itemDiscount":0,"isPopular":0,"showMC":0},"6731828":{"id":6731828,"name":"Egg Noodles","category":"Chinese","description":"","cloudinaryImageId":"","recommended":0,"inStock":1,"isVeg":2,"enabled":1,"displayOrder":0,"price":14000,"final_price":12600,"cropChoices":2,"itemScore":0,"itemDiscount":0,"isPopular":0,"showMC":0},"6731829":{"id":6731829,"name":"Egg Schezwan Noodles","category":"Chinese","description":"","cloudinaryImageId":"","recommended":0,"inStock":1,"isVeg":2,"enabled":1,"displayOrder":0,"price":16000,"final_price":14400,"cropChoices":2,"itemScore":0,"itemDiscount":0,"isPopular":0,"showMC":0},"6731830":{"id":6731830,"name":"Chicken Noodles","category":"Chinese","description":"","cloudinaryImageId":"","recommended":0,"inStock":1,"isVeg":0,"enabled":1,"displayOrder":0,"price":15000,"final_price":13500,"cropChoices":2,"itemScore":0,"itemDiscount":0,"isPopular":0,"showMC":0},"6731831":{"id":6731831,"name":"Chicken Schezwan Noodles","category":"Chinese","description":"","cloudinaryImageId":"","recommended":0,"inStock":1,"isVeg":0,"enabled":1,"displayOrder":0,"price":17000,"final_price":15300,"cropChoices":2,"itemScore":0,"itemDiscount":0,"isPopular":0,"showMC":0},"6731832":{"id":6731832,"name":"Mutton Noodles","category":"Chinese","description":"","cloudinaryImageId":"","recommended":0,"inStock":1,"isVeg":0,"enabled":1,"displayOrder":0,"price":18000,"final_price":16200,"cropChoices":2,"itemScore":0,"itemDiscount":0,"isPopular":0,"showMC":0},"6731833":{"id":6731833,"name":"Mutton Schezwan Noodles","category":"Chinese","description":"","cloudinaryImageId":"","recommended":0,"inStock":1,"isVeg":0,"enabled":1,"displayOrder":0,"price":20000,"final_price":18000,"cropChoices":2,"itemScore":0,"itemDiscount":0,"isPopular":0,"showMC":0},"6731834":{"id":6731834,"name":"Non Veg Mixed Noodles","category":"Chinese","description":"Contains Egg + Chicken + Mutton + Prawns","cloudinaryImageId":"","recommended":0,"inStock":1,"isVeg":0,"enabled":1,"displayOrder":0,"price":19000,"final_price":17100,"cropChoices":2,"itemScore":0,"itemDiscount":0,"isPopular":0,"showMC":0},"6731835":{"id":6731835,"name":"Non Veg Schezwan Mixed Noodles","category":"Chinese","description":"Contains Egg + Chicken + Mutton + Prawns","cloudinaryImageId":"","recommended":0,"inStock":1,"isVeg":0,"enabled":1,"displayOrder":0,"price":21000,"final_price":18900,"cropChoices":2,"itemScore":0,"itemDiscount":0,"isPopular":0,"showMC":0},"6731836":{"id":6731836,"name":"Veg American Chop suey","category":"Chinese","description":"","cloudinaryImageId":"","recommended":0,"inStock":1,"isVeg":1,"enabled":1,"displayOrder":0,"price":18000,"final_price":16200,"cropChoices":2,"itemScore":0,"itemDiscount":0,"isPopular":0,"showMC":0},"6731837":{"id":6731837,"name":"Veg Schezwan Chop suey","category":"Chinese","description":"","cloudinaryImageId":"","recommended":0,"inStock":1,"isVeg":1,"enabled":1,"displayOrder":0,"price":18000,"final_price":16200,"cropChoices":2,"itemScore":0,"itemDiscount":0,"isPopular":0,"showMC":0},"6731838":{"id":6731838,"name":"Veg Chinese Chop suey","category":"Chinese","description":"","cloudinaryImageId":"","recommended":0,"inStock":1,"isVeg":1,"enabled":1,"displayOrder":0,"price":18000,"final_price":16200,"cropChoices":2,"itemScore":0,"itemDiscount":0,"isPopular":0,"showMC":0},"6731839":{"id":6731839,"name":"Non Veg American Chop suey","category":"Chinese","description":"Contains Chicken","cloudinaryImageId":"","recommended":0,"inStock":1,"isVeg":0,"enabled":1,"displayOrder":0,"price":20000,"final_price":18000,"cropChoices":2,"itemScore":0,"itemDiscount":0,"isPopular":0,"showMC":0},"6731840":{"id":6731840,"name":"Non Veg Schezwan Chop suey","category":"Chinese","description":"Contains Chicken","cloudinaryImageId":"","recommended":0,"inStock":1,"isVeg":0,"enabled":1,"displayOrder":0,"price":20000,"final_price":18000,"cropChoices":2,"itemScore":0,"itemDiscount":0,"isPopular":0,"showMC":0},"6731841":{"id":6731841,"name":"Non Veg Chinese Chop suey","category":"Chinese","description":"Contains Chicken","cloudinaryImageId":"","recommended":0,"inStock":1,"isVeg":0,"enabled":1,"displayOrder":0,"price":20000,"final_price":18000,"cropChoices":2,"itemScore":0,"itemDiscount":0,"isPopular":0,"showMC":0},"6731846":{"id":6731846,"name":"Aarumah Sweet Naan","category":"Dessert","description":"Naan Stuffed With Shredded Coconut + Jaggery + Nuts & Till Seeds","cloudinaryImageId":"","recommended":0,"inStock":1,"isVeg":1,"enabled":1,"displayOrder":0,"price":12000,"final_price":10800,"cropChoices":2,"itemScore":0,"itemDiscount":0,"isPopular":0,"showMC":0},"6731847":{"id":6731847,"name":"Gulab Jamun","category":"Dessert","description":"","cloudinaryImageId":"","recommended":0,"inStock":1,"isVeg":1,"enabled":1,"displayOrder":0,"price":5000,"final_price":4500,"cropChoices":2,"itemScore":0,"itemDiscount":0,"isPopular":0,"showMC":0,"ribbon":{"text":"BESTSELLER","textColor":"#ffffff","topBackgroundColor":"#d53d4c","bottomBackgroundColor":"#b02331"}},"6731848":{"id":6731848,"name":"Carrot Halwa","category":"Dessert","description":"","cloudinaryImageId":"","recommended":0,"inStock":0,"isVeg":1,"enabled":1,"displayOrder":0,"price":8000,"final_price":7200,"nextAvailableAtMessage":"Next available at 12 noon, Sunday","cropChoices":2,"itemScore":0,"itemDiscount":0,"isPopular":0,"showMC":0,"ribbon":{"text":"BESTSELLER","textColor":"#ffffff","topBackgroundColor":"#d53d4c","bottomBackgroundColor":"#b02331"}},"6731849":{"id":6731849,"name":"Kasi Halwa","category":"Dessert","description":"","cloudinaryImageId":"","recommended":0,"inStock":0,"isVeg":1,"enabled":1,"displayOrder":0,"price":7500,"final_price":6700,"nextAvailableAtMessage":"Next available at 0 am, Sunday","cropChoices":2,"itemScore":0,"itemDiscount":0,"isPopular":0,"showMC":0},"6731850":{"id":6731850,"name":"Gulab Jamun with Ice cream","category":"Dessert","description":"","cloudinaryImageId":"","recommended":0,"inStock":1,"isVeg":1,"enabled":1,"displayOrder":0,"price":8000,"final_price":7200,"cropChoices":2,"itemScore":0,"itemDiscount":0,"isPopular":0,"showMC":0},"6731851":{"id":6731851,"name":"Fruit Salad with Ice cream","category":"Dessert","description":"","cloudinaryImageId":"","recommended":0,"inStock":1,"isVeg":1,"enabled":1,"displayOrder":0,"price":11000,"final_price":9900,"cropChoices":2,"itemScore":0,"itemDiscount":0,"isPopular":0,"showMC":0},"6731852":{"id":6731852,"name":"Falooda Ice cream","category":"Dessert","description":"","cloudinaryImageId":"","recommended":0,"inStock":1,"isVeg":1,"enabled":1,"displayOrder":0,"price":12000,"final_price":10800,"cropChoices":2,"itemScore":0,"itemDiscount":0,"isPopular":0,"showMC":0},"6731853":{"id":6731853,"name":"Aarumah Special Ice cream","category":"Dessert","description":"","cloudinaryImageId":"","recommended":0,"inStock":1,"isVeg":1,"enabled":1,"displayOrder":0,"price":15000,"final_price":13500,"cropChoices":2,"itemScore":0,"itemDiscount":0,"isPopular":0,"showMC":0},"6731854":{"id":6731854,"name":"Strawberry Ice cream","category":"Dessert","description":"","cloudinaryImageId":"","recommended":0,"inStock":1,"isVeg":1,"enabled":1,"displayOrder":0,"price":6500,"final_price":5800,"cropChoices":2,"itemScore":0,"itemDiscount":0,"isPopular":0,"showMC":0},"6731855":{"id":6731855,"name":"Vanilla Ice cream","category":"Dessert","description":"","cloudinaryImageId":"","recommended":0,"inStock":1,"isVeg":1,"enabled":1,"displayOrder":0,"price":6000,"final_price":5400,"cropChoices":2,"itemScore":0,"itemDiscount":0,"isPopular":0,"showMC":0},"6731856":{"id":6731856,"name":"Butterscotch Ice cream","category":"Dessert","description":"","cloudinaryImageId":"","recommended":0,"inStock":1,"isVeg":1,"enabled":1,"displayOrder":0,"price":6500,"final_price":5800,"cropChoices":2,"itemScore":0,"itemDiscount":0,"isPopular":0,"showMC":0},"6731857":{"id":6731857,"name":"Chocolate Ice cream","category":"Dessert","description":"","cloudinaryImageId":"","recommended":0,"inStock":1,"isVeg":1,"enabled":1,"displayOrder":0,"price":6500,"final_price":5800,"cropChoices":2,"itemScore":0,"itemDiscount":0,"isPopular":0,"showMC":0},"6731858":{"id":6731858,"name":"Spanish Delight Ice cream","category":"Dessert","description":"","cloudinaryImageId":"","recommended":0,"inStock":1,"isVeg":1,"enabled":1,"displayOrder":0,"price":8000,"final_price":7200,"cropChoices":2,"itemScore":0,"itemDiscount":0,"isPopular":0,"showMC":0},"6731859":{"id":6731859,"name":"Ice cream (Single Scoop)","category":"Dessert","description":"vanilla pista butterstcooch strawberry spanish chocolate","cloudinaryImageId":"","recommended":0,"inStock":1,"isVeg":1,"enabled":1,"displayOrder":0,"price":4000,"final_price":3600,"variants_new":{"exclude_list":[],"variant_groups":[{"group_id":"627472","name":"Choice of Ice cream","variations":[{"name":"Vanilla","price":0,"default":1,"id":"2212637","inStock":1,"isVeg":1,"order":1},{"name":"Pista","price":0,"default":0,"id":"2212638","inStock":1,"isVeg":1,"order":2},{"name":"Butterscotch","price":0,"default":0,"id":"2212639","inStock":1,"isVeg":1,"order":3},{"name":"Strawberry","price":0,"default":0,"id":"2212640","inStock":1,"isVeg":1,"order":4},{"name":"Spanish Delight","price":0,"default":0,"id":"2212641","inStock":1,"isVeg":1,"order":5},{"name":"Chocolate","price":0,"default":0,"id":"2212642","inStock":1,"isVeg":1,"order":6}]}]},"cropChoices":2,"itemScore":0,"itemDiscount":0,"isPopular":0,"showMC":0},"6731860":{"id":6731860,"name":"Spicy Orange","category":"Beverages","description":"Mixed of orange, coriander leaves, spices, sugar.","cloudinaryImageId":"","recommended":0,"inStock":1,"isVeg":1,"enabled":1,"displayOrder":0,"price":9000,"final_price":8100,"cropChoices":2,"itemScore":0,"itemDiscount":0,"isPopular":0,"showMC":0},"6731861":{"id":6731861,"name":"Rising Sun","category":"Beverages","description":"Mixed of orange, carrot and honey.","cloudinaryImageId":"","recommended":0,"inStock":1,"isVeg":1,"enabled":1,"displayOrder":0,"price":9000,"final_price":8100,"cropChoices":2,"itemScore":0,"itemDiscount":0,"isPopular":0,"showMC":0},"6731862":{"id":6731862,"name":"Mango Lassi","category":"Beverages","description":"Yogurt shacked with mango, sugar and ice.","cloudinaryImageId":"","recommended":0,"inStock":1,"isVeg":1,"enabled":1,"displayOrder":0,"price":9000,"final_price":8100,"cropChoices":2,"itemScore":0,"itemDiscount":0,"isPopular":0,"showMC":0},"6731863":{"id":6731863,"name":"Green Tea with Lemon","category":"Beverages","description":"","cloudinaryImageId":"","recommended":0,"inStock":1,"isVeg":1,"enabled":1,"displayOrder":0,"price":4000,"final_price":3600,"cropChoices":2,"itemScore":0,"itemDiscount":0,"isPopular":0,"showMC":0},"6731864":{"id":6731864,"name":"Cold Coffee","category":"Beverages","description":"","cloudinaryImageId":"","recommended":0,"inStock":1,"isVeg":1,"enabled":1,"displayOrder":0,"price":8500,"final_price":7600,"cropChoices":2,"itemScore":0,"itemDiscount":0,"isPopular":0,"showMC":0},"6731865":{"id":6731865,"name":"Milkshakes","category":"Beverages","description":"","cloudinaryImageId":"","recommended":0,"inStock":1,"isVeg":1,"enabled":1,"displayOrder":0,"price":8500,"final_price":7600,"variants_new":{"exclude_list":[],"variant_groups":[{"group_id":"627473","name":"Choice of Ice cream","variations":[{"name":"Vanilla","price":0,"default":1,"id":"2212643","inStock":1,"isVeg":1,"order":1},{"name":"Pista","price":0,"default":0,"id":"2212644","inStock":1,"isVeg":1,"order":2},{"name":"Butterscotch","price":0,"default":0,"id":"2212645","inStock":1,"isVeg":1,"order":3},{"name":"Strawberry","price":0,"default":0,"id":"2212646","inStock":1,"isVeg":1,"order":4},{"name":"Spanish Delight","price":0,"default":0,"id":"2212647","inStock":1,"isVeg":1,"order":5},{"name":"Chocolate","price":0,"default":0,"id":"2212648","inStock":1,"isVeg":1,"order":6}]}]},"cropChoices":2,"itemScore":0,"itemDiscount":0,"isPopular":0,"showMC":0},"6731866":{"id":6731866,"name":"Ice cream Milkshake","category":"Beverages","description":"","cloudinaryImageId":"","recommended":0,"inStock":1,"isVeg":1,"enabled":1,"displayOrder":0,"price":11000,"final_price":9900,"variants_new":{"exclude_list":[],"variant_groups":[{"group_id":"627474","name":"Choice of Ice cream","variations":[{"name":"Vanilla","price":0,"default":1,"id":"2212649","inStock":1,"isVeg":1,"order":1},{"name":"Pista","price":0,"default":0,"id":"2212650","inStock":1,"isVeg":1,"order":2},{"name":"Butterscotch","price":0,"default":0,"id":"2212651","inStock":1,"isVeg":1,"order":3},{"name":"Strawberry","price":0,"default":0,"id":"2212652","inStock":1,"isVeg":1,"order":4},{"name":"Spanish Delight","price":0,"default":0,"id":"2212653","inStock":1,"isVeg":1,"order":5},{"name":"Chocolate","price":0,"default":0,"id":"2212654","inStock":1,"isVeg":1,"order":6}]}]},"cropChoices":2,"itemScore":0,"itemDiscount":0,"isPopular":0,"showMC":0},"6731867":{"id":6731867,"name":"Watermelon Juice (Seasonal)","category":"Beverages","description":"","cloudinaryImageId":"","recommended":0,"inStock":1,"isVeg":1,"enabled":1,"displayOrder":0,"price":8000,"final_price":7200,"cropChoices":2,"itemScore":0,"itemDiscount":0,"isPopular":0,"showMC":0},"6731868":{"id":6731868,"name":"Pineapple Juice (Seasonal)","category":"Beverages","description":"","cloudinaryImageId":"","recommended":0,"inStock":1,"isVeg":1,"enabled":1,"displayOrder":0,"price":8000,"final_price":7200,"cropChoices":2,"itemScore":0,"itemDiscount":0,"isPopular":0,"showMC":0},"6731869":{"id":6731869,"name":"Mosambi Juice (Seasonal)","category":"Beverages","description":"","cloudinaryImageId":"","recommended":0,"inStock":1,"isVeg":1,"enabled":1,"displayOrder":0,"price":8000,"final_price":7200,"cropChoices":2,"itemScore":0,"itemDiscount":0,"isPopular":0,"showMC":0},"6731870":{"id":6731870,"name":"Fresh Lime Juice","category":"Beverages","description":"","cloudinaryImageId":"","recommended":0,"inStock":1,"isVeg":1,"enabled":1,"displayOrder":0,"price":3000,"final_price":2700,"cropChoices":2,"itemScore":0,"itemDiscount":0,"isPopular":0,"showMC":0},"6731871":{"id":6731871,"name":"Fresh Lime Soda","category":"Beverages","description":"","cloudinaryImageId":"","recommended":0,"inStock":1,"isVeg":1,"enabled":1,"displayOrder":0,"price":4500,"final_price":4000,"cropChoices":2,"itemScore":0,"itemDiscount":0,"isPopular":0,"showMC":0},"6731872":{"id":6731872,"name":"Mineral Water Bottle (1 Litre)","category":"Beverages","description":"","cloudinaryImageId":"","recommended":0,"inStock":1,"isVeg":1,"enabled":1,"displayOrder":0,"price":2500,"final_price":2200,"cropChoices":2,"itemScore":0,"itemDiscount":0,"isPopular":0,"showMC":0},"6731873":{"id":6731873,"name":"Apple Juice","category":"Beverages","description":"","cloudinaryImageId":"","recommended":0,"inStock":1,"isVeg":1,"enabled":1,"displayOrder":0,"price":7500,"final_price":6700,"cropChoices":2,"itemScore":0,"itemDiscount":0,"isPopular":0,"showMC":0},"6731874":{"id":6731874,"name":"Pomegranate Juice","category":"Beverages","description":"","cloudinaryImageId":"","recommended":0,"inStock":1,"isVeg":1,"enabled":1,"displayOrder":0,"price":7500,"final_price":6700,"cropChoices":2,"itemScore":0,"itemDiscount":0,"isPopular":0,"showMC":0},"6731875":{"id":6731875,"name":"Carrot Juice","category":"Beverages","description":"","cloudinaryImageId":"","recommended":0,"inStock":1,"isVeg":1,"enabled":1,"displayOrder":0,"price":8000,"final_price":7200,"cropChoices":2,"itemScore":0,"itemDiscount":0,"isPopular":0,"showMC":0},"6731876":{"id":6731876,"name":"Lime Mint Cool","category":"Beverages","description":"","cloudinaryImageId":"","recommended":0,"inStock":1,"isVeg":1,"enabled":1,"displayOrder":0,"price":4500,"final_price":4000,"cropChoices":2,"itemScore":0,"itemDiscount":0,"isPopular":0,"showMC":0},"6731877":{"id":6731877,"name":"Buttermilk-Aarumah Special","category":"Beverages","description":"","cloudinaryImageId":"","recommended":0,"inStock":1,"isVeg":1,"enabled":1,"displayOrder":0,"price":4000,"final_price":3600,"cropChoices":2,"itemScore":0,"itemDiscount":0,"isPopular":0,"showMC":0},"6731878":{"id":6731878,"name":"Lassi","category":"Beverages","description":"","cloudinaryImageId":"","recommended":0,"inStock":1,"isVeg":1,"enabled":1,"displayOrder":0,"price":4000,"final_price":3600,"cropChoices":2,"itemScore":0,"itemDiscount":0,"isPopular":0,"showMC":0},"6745550":{"id":6745550,"name":"Vanilla Ice cream","category":"Dessert","description":"","cloudinaryImageId":"","recommended":0,"inStock":1,"isVeg":1,"enabled":1,"displayOrder":0,"price":4000,"final_price":3600,"cropChoices":2,"itemScore":0,"itemDiscount":0,"isPopular":0,"showMC":0},"6745551":{"id":6745551,"name":"Pista Ice cream","category":"Dessert","description":"","cloudinaryImageId":"","recommended":0,"inStock":1,"isVeg":1,"enabled":1,"displayOrder":0,"price":4000,"final_price":3600,"cropChoices":2,"itemScore":0,"itemDiscount":0,"isPopular":0,"showMC":0},"6745552":{"id":6745552,"name":"Butterscotch Ice cream","category":"Dessert","description":"","cloudinaryImageId":"","recommended":0,"inStock":1,"isVeg":1,"enabled":1,"displayOrder":0,"price":4000,"final_price":3600,"cropChoices":2,"itemScore":0,"itemDiscount":0,"isPopular":0,"showMC":0},"6745553":{"id":6745553,"name":"Strawberry Ice cream","category":"Dessert","description":"","cloudinaryImageId":"","recommended":0,"inStock":1,"isVeg":1,"enabled":1,"displayOrder":0,"price":4000,"final_price":3600,"cropChoices":2,"itemScore":0,"itemDiscount":0,"isPopular":0,"showMC":0},"6745554":{"id":6745554,"name":"Spanish Delight Ice cream","category":"Dessert","description":"","cloudinaryImageId":"","recommended":0,"inStock":1,"isVeg":1,"enabled":1,"displayOrder":0,"price":4000,"final_price":3600,"cropChoices":2,"itemScore":0,"itemDiscount":0,"isPopular":0,"showMC":0},"6745555":{"id":6745555,"name":"Chocolate Ice cream","category":"Dessert","description":"","cloudinaryImageId":"","recommended":0,"inStock":1,"isVeg":1,"enabled":1,"displayOrder":0,"price":4000,"final_price":3600,"cropChoices":2,"itemScore":0,"itemDiscount":0,"isPopular":0,"showMC":0},"6745556":{"id":6745556,"name":"Vanilla Milkshake","category":"Beverages","description":"","cloudinaryImageId":"","recommended":0,"inStock":1,"isVeg":1,"enabled":1,"displayOrder":0,"price":8500,"final_price":7600,"cropChoices":2,"itemScore":0,"itemDiscount":0,"isPopular":0,"showMC":0},"6745557":{"id":6745557,"name":"Pista Milkshake","category":"Beverages","description":"","cloudinaryImageId":"","recommended":0,"inStock":1,"isVeg":1,"enabled":1,"displayOrder":0,"price":8500,"final_price":7600,"cropChoices":2,"itemScore":0,"itemDiscount":0,"isPopular":0,"showMC":0},"6745558":{"id":6745558,"name":"Butterscotch Milkshake","category":"Beverages","description":"","cloudinaryImageId":"","recommended":0,"inStock":1,"isVeg":1,"enabled":1,"displayOrder":0,"price":8500,"final_price":7600,"cropChoices":2,"itemScore":0,"itemDiscount":0,"isPopular":0,"showMC":0},"6745559":{"id":6745559,"name":"Strawberry Ice cream","category":"Beverages","description":"","cloudinaryImageId":"","recommended":0,"inStock":1,"isVeg":1,"enabled":1,"displayOrder":0,"price":8500,"final_price":7600,"cropChoices":2,"itemScore":0,"itemDiscount":0,"isPopular":0,"showMC":0},"6745560":{"id":6745560,"name":"Spanish Delight Ice cream","category":"Beverages","description":"","cloudinaryImageId":"","recommended":0,"inStock":1,"isVeg":1,"enabled":1,"displayOrder":0,"price":8500,"final_price":7600,"cropChoices":2,"itemScore":0,"itemDiscount":0,"isPopular":0,"showMC":0},"6745561":{"id":6745561,"name":"Chocolate Ice cream","category":"Beverages","description":"","cloudinaryImageId":"","recommended":0,"inStock":1,"isVeg":1,"enabled":1,"displayOrder":0,"price":8500,"final_price":7600,"cropChoices":2,"itemScore":0,"itemDiscount":0,"isPopular":0,"showMC":0},"6745576":{"id":6745576,"name":"Vanilla Ice cream Milkshake","category":"Beverages","description":"","cloudinaryImageId":"","recommended":0,"inStock":1,"isVeg":1,"enabled":1,"displayOrder":0,"price":11000,"final_price":9900,"cropChoices":2,"itemScore":0,"itemDiscount":0,"isPopular":0,"showMC":0},"6745577":{"id":6745577,"name":"Pista Ice cream Milkshake","category":"Beverages","description":"","cloudinaryImageId":"","recommended":0,"inStock":1,"isVeg":1,"enabled":1,"displayOrder":0,"price":11000,"final_price":9900,"cropChoices":2,"itemScore":0,"itemDiscount":0,"isPopular":0,"showMC":0},"6745578":{"id":6745578,"name":"Butterscotch Ice cream Milkshake","category":"Beverages","description":"","cloudinaryImageId":"","recommended":0,"inStock":1,"isVeg":1,"enabled":1,"displayOrder":0,"price":11000,"final_price":9900,"cropChoices":2,"itemScore":0,"itemDiscount":0,"isPopular":0,"showMC":0},"6745579":{"id":6745579,"name":"Strawberry Ice cream Milkshake","category":"Beverages","description":"","cloudinaryImageId":"","recommended":0,"inStock":1,"isVeg":1,"enabled":1,"displayOrder":0,"price":11000,"final_price":9900,"cropChoices":2,"itemScore":0,"itemDiscount":0,"isPopular":0,"showMC":0},"6745580":{"id":6745580,"name":"Spanish Delight Ice cream Milkshake","category":"Beverages","description":"","cloudinaryImageId":"","recommended":0,"inStock":1,"isVeg":1,"enabled":1,"displayOrder":0,"price":11000,"final_price":9900,"cropChoices":2,"itemScore":0,"itemDiscount":0,"isPopular":0,"showMC":0},"6745581":{"id":6745581,"name":"Chocolate Ice cream Milkshake","category":"Beverages","description":"","cloudinaryImageId":"","recommended":0,"inStock":1,"isVeg":1,"enabled":1,"displayOrder":0,"price":11000,"final_price":9900,"cropChoices":2,"itemScore":0,"itemDiscount":0,"isPopular":0,"showMC":0}},"collections":[{"name":"Recommended","type":"recommended","itemViews":[{"id":"6731659"},{"id":"6731660"},{"id":"6731674"},{"id":"6731675"},{"id":"6731677"},{"id":"6731680"},{"id":"6731683"},{"id":"6731696"},{"id":"6731732"},{"id":"6731736"},{"id":"6731750"},{"id":"6731768"},{"id":"6731773"},{"id":"6731788"}],"perRow":2},{"name":"Quick Bites","type":"category","itemViews":[{"id":"6731633"},{"id":"6731634"},{"id":"6731635"},{"id":"6731636"}],"perRow":2},{"name":"Soups","type":"category","subCollections":[{"name":"Veg","type":"subcategory","itemViews":[{"id":"6731637"},{"id":"6731638"},{"id":"6731639"},{"id":"6731640"},{"id":"6731641"},{"id":"6731642"}]},{"name":"Egg","type":"subcategory","itemViews":[{"id":"6731643"}]},{"name":"Non-Veg","type":"subcategory","itemViews":[{"id":"6731644"},{"id":"6731645"},{"id":"6731646"},{"id":"6731647"},{"id":"6731648"},{"id":"6731649"},{"id":"6731650"},{"id":"6731651"},{"id":"6731652"}]}],"perRow":2},{"name":"Salad","type":"category","subCollections":[{"name":"Veg","type":"subcategory","itemViews":[{"id":"6731653"},{"id":"6731654"},{"id":"6731656"}]},{"name":"Non-Veg","type":"subcategory","itemViews":[{"id":"6731657"}]}],"perRow":2},{"name":"Indian","type":"category","subCollections":[{"name":"Chicken Starters","type":"subcategory","itemViews":[{"id":"6731658"},{"id":"6731659"},{"id":"6731660"},{"id":"6731661"},{"id":"6731662"},{"id":"6731663"},{"id":"6731664"},{"id":"6731665"},{"id":"6731666"},{"id":"6731667"},{"id":"6731668"}]},{"name":"Mutton Starters","type":"subcategory","itemViews":[{"id":"6731669"},{"id":"6731670"},{"id":"6731671"},{"id":"6731672"},{"id":"6731673"},{"id":"6731674"}]},{"name":"Seafood Starters","type":"subcategory","itemViews":[{"id":"6731675"},{"id":"6731676"},{"id":"6731677"},{"id":"6731678"},{"id":"6731679"}]},{"name":"Non-Veg Tandoor","type":"subcategory","itemViews":[{"id":"6731680"},{"id":"6731681"},{"id":"6731682"},{"id":"6731683"},{"id":"6731684"},{"id":"6731685"},{"id":"6731686"}]},{"name":"BBQ Starters","type":"subcategory","itemViews":[{"id":"6731687"},{"id":"6731688"},{"id":"6731689"},{"id":"6731690"},{"id":"6731691"},{"id":"6731692"},{"id":"6731693"},{"id":"6731694"}]},{"name":"Platter","type":"subcategory","itemViews":[{"id":"6731695"}]},{"name":"Veg Main Course","type":"subcategory","itemViews":[{"id":"6731696"},{"id":"6731697"},{"id":"6731698"},{"id":"6731699"},{"id":"6731700"},{"id":"6731701"},{"id":"6731702"},{"id":"6731703"}]},{"name":"Egg Main Course","type":"subcategory","itemViews":[{"id":"6731704"}]},{"name":"Chicken Main Course","type":"subcategory","itemViews":[{"id":"6731705"},{"id":"6731706"},{"id":"6731707"},{"id":"6731708"},{"id":"6731709"},{"id":"6731710"},{"id":"6731711"},{"id":"6731712"},{"id":"6731713"}]},{"name":"Mutton Main Course","type":"subcategory","itemViews":[{"id":"6731714"},{"id":"6731715"},{"id":"6731716"},{"id":"6731717"},{"id":"6731718"},{"id":"6731719"},{"id":"6731721"},{"id":"6731722"}]},{"name":"Seafood Main Course","type":"subcategory","itemViews":[{"id":"6731723"},{"id":"6731724"},{"id":"6731725"},{"id":"6731726"},{"id":"6731727"},{"id":"6731728"},{"id":"6731729"},{"id":"6731730"},{"id":"6731731"},{"id":"6731732"}]},{"name":"Rice","type":"subcategory","itemViews":[{"id":"6731733"},{"id":"6731734"},{"id":"6731735"}]},{"name":"Biryanis","type":"subcategory","itemViews":[{"id":"6731736"},{"id":"6731737"},{"id":"6731738"},{"id":"6731740"},{"id":"6731741"},{"id":"6731742"},{"id":"6731739"}]},{"name":"Indian Breads","type":"subcategory","itemViews":[{"id":"6731655"},{"id":"6731743"},{"id":"6731744"},{"id":"6731745"},{"id":"6731746"},{"id":"6731747"},{"id":"6731748"},{"id":"6731749"},{"id":"6731750"},{"id":"6731751"},{"id":"6731752"},{"id":"6731753"},{"id":"6731754"}]}],"perRow":2},{"name":"Chinese","type":"category","subCollections":[{"name":"Veg Starters","type":"subcategory","itemViews":[{"id":"6731755"},{"id":"6731756"},{"id":"6731757"},{"id":"6731758"},{"id":"6731759"},{"id":"6731760"},{"id":"6731761"},{"id":"6731762"},{"id":"6731763"},{"id":"6731764"},{"id":"6731765"},{"id":"6731766"}]},{"name":"Egg Starters","type":"subcategory","itemViews":[{"id":"6731767"}]},{"name":"Non-Veg Starters","type":"subcategory","itemViews":[{"id":"6731768"},{"id":"6731769"},{"id":"6731770"},{"id":"6731771"},{"id":"6731772"},{"id":"6731773"},{"id":"6731774"},{"id":"6731775"},{"id":"6731779"},{"id":"6731781"},{"id":"6731782"},{"id":"6731783"},{"id":"6731784"},{"id":"6731785"},{"id":"6731786"},{"id":"6731787"},{"id":"6731788"},{"id":"6731789"},{"id":"6731790"},{"id":"6731791"}]},{"name":"Veg Main Course","type":"subcategory","itemViews":[{"id":"6731792"},{"id":"6731793"},{"id":"6731794"},{"id":"6731795"}]},{"name":"Non-Veg Main Course","type":"subcategory","itemViews":[{"id":"6731796"},{"id":"6731797"},{"id":"6731798"},{"id":"6731799"},{"id":"6731800"},{"id":"6731801"},{"id":"6731802"}]},{"name":"Fried Rice","type":"subcategory","itemViews":[{"id":"6731803"},{"id":"6731804"},{"id":"6731805"},{"id":"6731806"},{"id":"6731807"},{"id":"6731808"},{"id":"6731809"},{"id":"6731810"},{"id":"6731811"},{"id":"6731812"},{"id":"6731813"},{"id":"6731814"},{"id":"6731815"},{"id":"6731816"},{"id":"6731817"},{"id":"6731818"},{"id":"6731819"},{"id":"6731820"}]},{"name":"Noodles","type":"subcategory","itemViews":[{"id":"6731821"},{"id":"6731822"},{"id":"6731823"},{"id":"6731824"},{"id":"6731825"},{"id":"6731826"},{"id":"6731827"},{"id":"6731828"},{"id":"6731829"},{"id":"6731830"},{"id":"6731831"},{"id":"6731832"},{"id":"6731833"},{"id":"6731834"},{"id":"6731835"}]},{"name":"Chop suey","type":"subcategory","itemViews":[{"id":"6731836"},{"id":"6731837"},{"id":"6731838"},{"id":"6731839"},{"id":"6731840"},{"id":"6731841"}]}],"perRow":2},{"name":"Dessert","type":"category","itemViews":[{"id":"6731846"},{"id":"6731847"},{"id":"6731850"},{"id":"6731851"},{"id":"6731852"},{"id":"6731853"},{"id":"6731854"},{"id":"6731855"},{"id":"6731856"},{"id":"6731857"},{"id":"6731858"},{"id":"6731859"},{"id":"6745550"},{"id":"6745551"},{"id":"6745552"},{"id":"6745553"},{"id":"6745554"},{"id":"6745555"},{"id":"6731848"},{"id":"6731849"}],"perRow":2},{"name":"Beverages","type":"category","subCollections":[{"name":"Refershments","type":"subcategory","itemViews":[{"id":"6731860"},{"id":"6731861"},{"id":"6731862"},{"id":"6731863"},{"id":"6731864"}]},{"name":"Milkshakes","type":"subcategory","itemViews":[{"id":"6731865"},{"id":"6745556"},{"id":"6745557"},{"id":"6745558"},{"id":"6745559"},{"id":"6745560"},{"id":"6745561"}]},{"name":"Ice cream Milkshakes","type":"subcategory","itemViews":[{"id":"6731866"},{"id":"6745576"},{"id":"6745577"},{"id":"6745578"},{"id":"6745579"},{"id":"6745580"},{"id":"6745581"}]},{"name":"Juice","type":"subcategory","itemViews":[{"id":"6731867"},{"id":"6731868"},{"id":"6731869"},{"id":"6731870"},{"id":"6731871"},{"id":"6731872"},{"id":"6731873"},{"id":"6731874"},{"id":"6731875"},{"id":"6731876"},{"id":"6731877"},{"id":"6731878"}]}],"perRow":2}]},"tags":[],"selectedPreOrderSlot":null,"similarRestaurantAvailable":null,"preorderable":false,"select":false,"slotInvalid":false},"tid":"856e8f62-247e-48b1-9bbb-e17e02cbc54a","sid":"73z753fd-6de3-4146-b013-66b6289232f0","deviceId":"7b099041-3c4e-4869-9d3e-00afbd67a145"}